{
  "city": "Vancouver",
  "state": "Washington",
  "state_code": "WA",
  "city_slug": "vancouver",
  "state_slug": "washington",
  "firm_count": 20,
  "firms": [
    {
      "slug": "global-taxes-llc",
      "name": "Global Taxes LLC",
      "category": "Tax preparation service",
      "phone": "+1 212-803-3327",
      "site": "http://globaltaxes.com/",
      "address": "745 5th Ave 5th Fl, New York, NY 10151",
      "latitude": 40.7632714,
      "longitude": -73.9735492,
      "rating": 4.3,
      "reviews": 19,
      "logo": "https://lh4.googleusercontent.com/-eKQuGuWOKcE/AAAAAAAAAAI/AAAAAAAAAAA/aYF6mQRTsBw/s44-p-k-no-ns-nd/photo.jpg",
      "photo": "https://lh3.googleusercontent.com/gps-cs-s/APNQkAFbNtH26jV3feaDHajWB69qYbukcWTavY8cDZTwLPyuK7guCtlj0sooYwvrUarsRe5a8JoN04GFfIXY4JVeR5vAtBhD0Y_kc2TOr7rvMHXBJIgmHoCA8GjTqho6Q4LF2nEi7w7O=w800-h500-k-no",
      "working_hours": {
        "Friday": "10AM-5PM",
        "Monday": "10AM-5PM",
        "Saturday": "Closed",
        "Sunday": "Closed",
        "Thursday": "10AM-5PM",
        "Tuesday": "10AM-5PM",
        "Wednesday": "10AM-5PM"
      },
      "reviews_per_score": {
        "1": 3,
        "2": 0,
        "3": 0,
        "4": 1,
        "5": 15
      },
      "business_status": "OPERATIONAL",
      "is_verified": true,
      "is_claimed": true
    },
    {
      "slug": "opsahl-dawson-vancouver",
      "name": "Opsahl Dawson - Vancouver",
      "category": "Accounting firm",
      "phone": "+1 360-737-8007",
      "site": "https://www.opsahldawson.com/",
      "address": "7701 NE Greenwood Dr Ste 200, Vancouver, WA 98662",
      "latitude": 45.6526132,
      "longitude": -122.5938544,
      "rating": 4.4,
      "reviews": 72,
      "logo": "https://lh5.googleusercontent.com/-gHMxBu-HiKQ/AAAAAAAAAAI/AAAAAAAAAAA/O7HZ-zujBqc/s44-p-k-no-ns-nd/photo.jpg",
      "photo": "https://lh3.googleusercontent.com/gps-cs-s/APNQkAGQMe1Jgj99cftfvQKmMQdaud9iZQMGvCFsXWaBmoDTLm8F4itPvoK4D1BWzAozz569Toipns__LQ2eBUWeAq0nV87LbLyWYjZFkR-xm0s4yqTv7eyTbzgQ_i3AsWsWTlbDX-JzLw=w800-h500-k-no",
      "working_hours": {
        "Friday": "8:30AM-5PM",
        "Monday": "8:30AM-5PM",
        "Saturday": "Closed",
        "Sunday": "Closed",
        "Thursday": "8:30AM-5PM",
        "Tuesday": "8:30AM-5PM",
        "Wednesday": "8:30AM-5PM"
      },
      "reviews_per_score": {
        "1": 11,
        "2": 0,
        "3": 0,
        "4": 2,
        "5": 59
      },
      "business_status": "OPERATIONAL",
      "is_verified": true,
      "is_claimed": true
    },
    {
      "slug": "kelli-loo-cpa",
      "name": "Kelli Loo CPA",
      "category": "Certified public accountant",
      "phone": "",
      "site": "http://www.kelliloocpa.com/",
      "address": "15640 NE Fourth Plain Blvd 106 #480, Vancouver, WA 98682",
      "latitude": 45.6731979,
      "longitude": -122.51250139999999,
      "rating": 5,
      "reviews": 80,
      "logo": "https://lh4.googleusercontent.com/-buv7983NPvI/AAAAAAAAAAI/AAAAAAAAAAA/3RgL2OE8oAw/s44-p-k-no-ns-nd/photo.jpg",
      "photo": "https://lh3.googleusercontent.com/gps-cs-s/APNQkAFoq6R-xuULF_ofGqdcViFua7H0ZCkfPaDMiiLiC4Ub7J7tEqWwvbYpE69m1sivR2SoS3T0GZ94jYdc-Zf-3wOOgAFMf6pvdeyRj1gfo9_l-CHbBBtG5Pwi8Oi7-fkwBnrFHnXU=w800-h500-k-no",
      "working_hours": {
        "Monday": "Closed",
        "Tuesday": "Closed",
        "Wednesday": "Closed",
        "Thursday": "Closed",
        "Friday": "Closed",
        "Saturday": "Closed",
        "Sunday": "Closed"
      },
      "reviews_per_score": {
        "1": 0,
        "2": 0,
        "3": 0,
        "4": 0,
        "5": 80
      },
      "business_status": "OPERATIONAL",
      "is_verified": true,
      "is_claimed": true
    },
    {
      "slug": "shields-tax-and-cpa-pllc",
      "name": "Shields Tax & CPA, PLLC",
      "category": "Certified public accountant",
      "phone": "+1 360-696-3877",
      "site": "http://www.shieldstaxcpa.com/",
      "address": "910 NE Minnehaha St # 12, Vancouver, WA 98665",
      "latitude": 45.6673761,
      "longitude": -122.6621449,
      "rating": 4.8,
      "reviews": 87,
      "logo": "https://lh5.googleusercontent.com/-7fSf6uObnjE/AAAAAAAAAAI/AAAAAAAAAAA/w-zrBYorBZ8/s44-p-k-no-ns-nd/photo.jpg",
      "photo": "https://lh3.googleusercontent.com/gps-cs-s/APNQkAGWvjkNf3veMzDR0wnlthY_EXmz63xc42w6Tnc3zuGKi_SIsER1QdPe8gOdLZ0YEeMv2GvytXngT-RH6BmYxQmIj2FRshLeNZb10uuM7Z7OuyMeF-pV3VxmH_sI2OKE7j1tNCk=w800-h500-k-no",
      "working_hours": {
        "Friday": "9AM-5PM",
        "Monday": "9AM-5PM",
        "Saturday": "Closed",
        "Sunday": "Closed",
        "Thursday": "9AM-5PM",
        "Tuesday": "9AM-5PM",
        "Wednesday": "9AM-5PM"
      },
      "reviews_per_score": {
        "1": 3,
        "2": 1,
        "3": 1,
        "4": 3,
        "5": 79
      },
      "business_status": "OPERATIONAL",
      "is_verified": true,
      "is_claimed": true
    },
    {
      "slug": "dmp-management-dba-allied-accounting-and-tax-service",
      "name": "DMP Management DBA Allied Accounting & Tax Service",
      "category": "Accountant",
      "phone": "+1 360-213-1040",
      "site": "",
      "address": "4400 NE 77th Ave, Vancouver, WA 98662",
      "latitude": 45.6539705,
      "longitude": -122.59495,
      "rating": 4.8,
      "reviews": 94,
      "logo": "https://lh4.googleusercontent.com/-WIKqcsKUHDA/AAAAAAAAAAI/AAAAAAAAAAA/0vqG9GgI7EA/s44-p-k-no-ns-nd/photo.jpg",
      "photo": "https://lh3.googleusercontent.com/gps-cs-s/APNQkAEIaHcnyeyM0_pLzW13dMB5-1IrPr-csbZufgVE6dcl0oEfp9yConjERQz8tuGkGnAruzsn0adKq6GFFOj6Ihzr9CZ6sJhumkeCw1VukYpaH230VWp491KdOMV3np2sqaubjoU=w800-h500-k-no",
      "working_hours": {
        "Friday": "8:30AM-4:30PM",
        "Monday": "8:30AM-4:30PM",
        "Saturday": "Closed",
        "Sunday": "Closed",
        "Thursday": "8:30AM-4:30PM",
        "Tuesday": "8:30AM-4:30PM",
        "Wednesday": "8:30AM-4:30PM"
      },
      "reviews_per_score": {
        "1": 3,
        "2": 1,
        "3": 2,
        "4": 2,
        "5": 86
      },
      "business_status": "OPERATIONAL",
      "is_verified": true,
      "is_claimed": true
    },
    {
      "slug": "rjl-accounting-and-tax",
      "name": "RJL Accounting & Tax",
      "category": "Accountant",
      "phone": "+1 360-803-3214",
      "site": "https://rjlaccountingtax.com/",
      "address": "4001 Main St S323, Vancouver, WA 98663",
      "latitude": 45.6516032,
      "longitude": -122.66678549999999,
      "rating": 4.8,
      "reviews": 71,
      "logo": "https://lh4.googleusercontent.com/-rE3uohu0UuM/AAAAAAAAAAI/AAAAAAAAAAA/XM6ognOLEpA/s44-p-k-no-ns-nd/photo.jpg",
      "photo": "https://lh3.googleusercontent.com/gps-cs-s/APNQkAFK4zWjipkpJRq_luWb2j_dQK046vfwIkkS0rLS21KDDPembPhm7ehgL2wFek0iW8R6pnR5Vg7CsUey56-sZYnz_QlA4FEhBJEYa4Nxs5NMOr4di0oExLrNsx_qCnRSqVNZ6wk6BLXC3cjI=w800-h500-k-no",
      "working_hours": {
        "Friday": "9AM-12PM",
        "Monday": "9AM-4PM",
        "Saturday": "Closed",
        "Sunday": "Closed",
        "Thursday": "9AM-4PM",
        "Tuesday": "9AM-4PM",
        "Wednesday": "9AM-4PM"
      },
      "reviews_per_score": {
        "1": 2,
        "2": 0,
        "3": 2,
        "4": 1,
        "5": 66
      },
      "business_status": "OPERATIONAL",
      "is_verified": true,
      "is_claimed": true
    },
    {
      "slug": "john-schahfer-tax-services",
      "name": "John Schahfer Tax Services",
      "category": "Tax preparation service",
      "phone": "+1 360-699-5203",
      "site": "",
      "address": "8321 NE Hwy 99, Vancouver, WA 98665",
      "latitude": 45.683190499999995,
      "longitude": -122.6605539,
      "rating": 4.8,
      "reviews": 24,
      "logo": "https://lh6.googleusercontent.com/-iJd6lcJTtQI/AAAAAAAAAAI/AAAAAAAAAAA/gvmufjL0YG4/s44-p-k-no-ns-nd/photo.jpg",
      "photo": "https://lh3.googleusercontent.com/gps-cs-s/APNQkAGaFN71-PRG8U4yEVQ9S27zAer8ztWED4ZAV7DpTePITsyLB0xq8eib7IDEFkRYw9MPEf-oZPClfAO7gYHRWrFeKqMsqrnB_Fmbuj80FwQz4UVhb13eD41Ski7JmSWD9XSJJ1A=w800-h500-k-no",
      "working_hours": {
        "Friday": "9AM-3PM",
        "Monday": "9AM-5PM",
        "Saturday": "Closed",
        "Sunday": "Closed",
        "Thursday": "9AM-5PM",
        "Tuesday": "9AM-5PM",
        "Wednesday": "9AM-5PM"
      },
      "reviews_per_score": {
        "1": 1,
        "2": 0,
        "3": 0,
        "4": 1,
        "5": 22
      },
      "business_status": "OPERATIONAL",
      "is_verified": true,
      "is_claimed": true
    },
    {
      "slug": "peterson-and-associates-ps",
      "name": "Peterson & Associates, P.S.",
      "category": "Tax preparation service",
      "phone": "+1 360-574-0644",
      "site": "http://www.vancouvercpa.com/%3Futm_source%3Dgoogle%26utm_medium%3Dorganic%26utm_content%3Dgmb",
      "address": "14201 NE 20th Ave Ste B101, Vancouver, WA 98686",
      "latitude": 45.7238976,
      "longitude": -122.65025329999999,
      "rating": 4.4,
      "reviews": 16,
      "logo": "https://lh6.googleusercontent.com/-6Lnv6SqRx-E/AAAAAAAAAAI/AAAAAAAAAAA/XMBcSuAi_1w/s44-p-k-no-ns-nd/photo.jpg",
      "photo": "https://lh3.googleusercontent.com/gps-cs-s/APNQkAHpuSZKMEUqh-7_LZ6qwAWNrmLLZerXxI03EmojIst0DvY_VhdpaPDcZLnwQrlGlZu5sCHo6vLdY4HjVDArxm4qrK31_i7ph9UZnaPFLY-ZL8fCzDo_K_UpHzy-Fo17XThDfwk=w800-h500-k-no",
      "working_hours": {
        "Friday": "8AM-6PM",
        "Monday": "8AM-5PM",
        "Saturday": "Closed",
        "Sunday": "Closed",
        "Thursday": "8AM-6PM",
        "Tuesday": "8AM-6PM",
        "Wednesday": "8AM-6PM"
      },
      "reviews_per_score": {
        "1": 1,
        "2": 2,
        "3": 0,
        "4": 0,
        "5": 13
      },
      "business_status": "OPERATIONAL",
      "is_verified": true,
      "is_claimed": true
    },
    {
      "slug": "lewis-group-cpas-pc",
      "name": "Lewis Group CPAs, P.C.",
      "category": "Certified public accountant",
      "phone": "+1 360-896-8221",
      "site": "https://lewisgroupcpas.com/",
      "address": "600 NE 99th St, Vancouver, WA 98665",
      "latitude": 45.6932882,
      "longitude": -122.665859,
      "rating": 3.9,
      "reviews": 34,
      "logo": "https://lh6.googleusercontent.com/-I135x5O7Rq0/AAAAAAAAAAI/AAAAAAAAAAA/VAOr1MAozqg/s44-p-k-no-ns-nd/photo.jpg",
      "photo": "https://lh3.googleusercontent.com/gps-cs-s/APNQkAGu_EMOA0iJDvZNO66sze5ICXJc8xWRk39fIHOMwpgka6Edy-sR-0tSYtI7a5Q3R3728o0Ow1v6Y3wPMHnHlgkbHG677WUYj7rQkVwZ5JdtWJ88UdqQQUkfbZMmFI0J0j6sPAGsn5eJ0bE_=w800-h500-k-no",
      "working_hours": {
        "Friday": "Closed",
        "Monday": "8AM-4PM",
        "Saturday": "Closed",
        "Sunday": "Closed",
        "Thursday": "8AM-4PM",
        "Tuesday": "8AM-4PM",
        "Wednesday": "8AM-4PM"
      },
      "reviews_per_score": {
        "1": 8,
        "2": 1,
        "3": 1,
        "4": 0,
        "5": 24
      },
      "business_status": "OPERATIONAL",
      "is_verified": true,
      "is_claimed": true
    },
    {
      "slug": "the-bookkeeping-company-tax-strategies-and-planning",
      "name": "The Bookkeeping Company: Tax Strategies & Planning",
      "category": "Financial advisor",
      "phone": "+1 360-524-9889",
      "site": "https://thebookkeepingcomp.org/",
      "address": "18523 NE 65th St, Vancouver, WA 98682",
      "latitude": 45.669331899999996,
      "longitude": -122.4823538,
      "rating": 4.9,
      "reviews": 70,
      "logo": "https://lh3.googleusercontent.com/-oewRsy96Pj8/AAAAAAAAAAI/AAAAAAAAAAA/EpbIS5kGxiE/s44-p-k-no-ns-nd/photo.jpg",
      "photo": "https://lh3.googleusercontent.com/gps-cs-s/APNQkAFflU_C2hEsH3dTuiYQAETuugntc7dofDWD_jt49LZVhUSQXvMQ5KFsPT7U6o0PZsjrGF1x3nlD_RGGEEX4gSAtDZ_DQd4P5xvVrwkAIBYHgXg4-5kYDc6B2V6Rd69eS_2gRZbU=w800-h500-k-no",
      "working_hours": {
        "Friday": "10AM-5:30PM",
        "Monday": "10AM-5:30PM",
        "Saturday": "10AM-4PM",
        "Sunday": "Closed",
        "Thursday": "10AM-5:30PM",
        "Tuesday": "10AM-5:30PM",
        "Wednesday": "10AM-5:30PM"
      },
      "reviews_per_score": {
        "1": 1,
        "2": 0,
        "3": 1,
        "4": 1,
        "5": 67
      },
      "business_status": "OPERATIONAL",
      "is_verified": true,
      "is_claimed": true
    },
    {
      "slug": "northwest-accounting-and-tax-service",
      "name": "Northwest Accounting & Tax Service",
      "category": "Tax preparation",
      "phone": "+1 360-694-8206",
      "site": "https://nwatax.net/",
      "address": "1307 NE 78th St b12, Vancouver, WA 98665",
      "latitude": 45.678138,
      "longitude": -122.658234,
      "rating": 4.5,
      "reviews": 85,
      "logo": "https://lh6.googleusercontent.com/-g8LH2oF_43k/AAAAAAAAAAI/AAAAAAAAAAA/09uABPYFt_Q/s44-p-k-no-ns-nd/photo.jpg",
      "photo": "https://lh3.googleusercontent.com/gps-cs-s/APNQkAF_7IlL_3OyUptx-DiyRDtmQ6BXU1vj-ihwGgUsy1L4wLMpd4hClx8OabPUaaLQY9w799C3h6QDP57u3YigfXLL919tv-W4xzmkQfmMrkQVWBVzZZROPyjMYmlwt-7jsdnxtBIVGw=w800-h500-k-no",
      "working_hours": {
        "Friday": "9AM-3PM",
        "Monday": "9AM-5PM",
        "Saturday": "Closed",
        "Sunday": "Closed",
        "Thursday": "9AM-5PM",
        "Tuesday": "9AM-5PM",
        "Wednesday": "9AM-5PM"
      },
      "reviews_per_score": {
        "1": 7,
        "2": 1,
        "3": 2,
        "4": 5,
        "5": 70
      },
      "business_status": "OPERATIONAL",
      "is_verified": true,
      "is_claimed": true
    },
    {
      "slug": "lindas-tax-service",
      "name": "Linda's Tax Service",
      "category": "Accountant",
      "phone": "+1 360-818-2471",
      "site": "https://lindastaxservice.com/vancouver-wa/accountant/",
      "address": "6314 NE 137th Ave, Vancouver, WA 98682",
      "latitude": 45.6688665,
      "longitude": -122.53210139999999,
      "rating": 4.5,
      "reviews": 404,
      "logo": "https://lh6.googleusercontent.com/-xKxtiLJF9tg/AAAAAAAAAAI/AAAAAAAAAAA/oQexgTiVEw8/s44-p-k-no-ns-nd/photo.jpg",
      "photo": "https://lh3.googleusercontent.com/gps-cs-s/APNQkAElaYOj7XSkpi8A0wf89TmtxJnp4x1Tt4_ix6TrLqBe-40H7Ux6aRJPsC1JzcRg2w7z0X55lv4jp5XUOXL4OEUnGLXSsqyJDUbR5-zrULEQSe1uvvnEz3_-8Ih2zjvE2EkKV-a4=w800-h500-k-no",
      "working_hours": {
        "Friday": "9AM-6PM",
        "Monday": "9AM-6PM",
        "Saturday": "10AM-6PM",
        "Sunday": "Closed",
        "Thursday": "9AM-6PM",
        "Tuesday": "9AM-6PM",
        "Wednesday": "9AM-6PM"
      },
      "reviews_per_score": {
        "1": 36,
        "2": 5,
        "3": 4,
        "4": 17,
        "5": 342
      },
      "business_status": "OPERATIONAL",
      "is_verified": true,
      "is_claimed": true
    },
    {
      "slug": "blackbird-accounting-pllc",
      "name": "Blackbird Accounting PLLC",
      "category": "Tax preparation service",
      "phone": "+1 360-433-2659",
      "site": "http://www.blackbirdcpas.com/",
      "address": "11700 NE 95th St #140, Vancouver, WA 98682",
      "latitude": 45.6911741,
      "longitude": -122.55220299999999,
      "rating": 5,
      "reviews": 13,
      "logo": "https://lh3.googleusercontent.com/-DXVzKWt7uF0/AAAAAAAAAAI/AAAAAAAAAAA/E23lRIqo0Yk/s44-p-k-no-ns-nd/photo.jpg",
      "photo": "https://lh3.googleusercontent.com/gps-cs-s/APNQkAHMDS3unGpuISoKt8RblVHAvJCJIemYamEWtjmnORGdhkB9GGJMvjef4bVr7dAQX4XgatUEBSca9juX7M6z7sSM7aH1oOwMoA-nLw3EyemS6zgOc77H22HEy8KAcdeTjerQ7Nx7=w800-h500-k-no",
      "working_hours": {
        "Friday": "8AM-5PM",
        "Monday": "8AM-5PM",
        "Saturday": "Closed",
        "Sunday": "Closed",
        "Thursday": "8AM-5PM",
        "Tuesday": "8AM-5PM",
        "Wednesday": "8AM-5PM"
      },
      "reviews_per_score": {
        "1": 0,
        "2": 0,
        "3": 0,
        "4": 0,
        "5": 13
      },
      "business_status": "OPERATIONAL",
      "is_verified": true,
      "is_claimed": true
    },
    {
      "slug": "green-taxes-cpas",
      "name": "Green Taxes CPAs",
      "category": "Tax preparation service",
      "phone": "+1 360-824-0022",
      "site": "http://www.greentaxescpa.com/",
      "address": "303 E 16th St #402, Vancouver, WA 98663",
      "latitude": 45.6332118,
      "longitude": -122.6686589,
      "rating": 5,
      "reviews": 31,
      "logo": "https://lh4.googleusercontent.com/-5WYlVRuyiEA/AAAAAAAAAAI/AAAAAAAAAAA/MWV9fsGX7z8/s44-p-k-no-ns-nd/photo.jpg",
      "photo": "https://lh3.googleusercontent.com/gps-cs-s/APNQkAG-B78Bjf-QlmX06FUXFcW9tqb6HH2EL4EzS53IrHo7fU1WceIcjJ-Ch5z9WYzXAPuoUml3QZ868p-4vdCSQkFckBcXWYCuFFAu-f_dsDjT5mU8DxLy540Hiws86EScQ2l8MI4DoA=w800-h500-k-no",
      "working_hours": {
        "Friday": "9AM-5PM",
        "Monday": "9AM-5PM",
        "Saturday": "Closed",
        "Sunday": "Closed",
        "Thursday": "9AM-5PM",
        "Tuesday": "9AM-5PM",
        "Wednesday": "9AM-5PM"
      },
      "reviews_per_score": {
        "1": 0,
        "2": 0,
        "3": 0,
        "4": 0,
        "5": 31
      },
      "business_status": "OPERATIONAL",
      "is_verified": true,
      "is_claimed": true
    },
    {
      "slug": "brewer-caley-cpas",
      "name": "Brewer Caley CPAs",
      "category": "Certified public accountant",
      "phone": "+1 360-695-0065",
      "site": "http://www.brewercaley.com/",
      "address": "613 E McLoughlin Blvd, Vancouver, WA 98663",
      "latitude": 45.6346366,
      "longitude": -122.6651984,
      "rating": 4.4,
      "reviews": 7,
      "logo": "https://lh4.googleusercontent.com/-H2OEyg3PMXQ/AAAAAAAAAAI/AAAAAAAAAAA/aRW7zpY8V_w/s44-p-k-no-ns-nd/photo.jpg",
      "photo": "https://lh3.googleusercontent.com/gps-cs-s/APNQkAHcWTWmovj12Brfsy_sO2i0w_ixkPbpRatQ-SYzxu9oW7nrWXgp2XvchMlrPTOufcBaec5p6dJ-JOhEP-FC5BAdaCaWVkLZmA7aKHtOiqqgDgt6jbP2sOo9hfpp1VKfUyUhY_QT=w800-h500-k-no",
      "working_hours": {
        "Friday": "8:30AM-5PM",
        "Monday": "8:30AM-5PM",
        "Saturday": "Closed",
        "Sunday": "Closed",
        "Thursday": "8:30AM-5PM",
        "Tuesday": "8:30AM-5PM",
        "Wednesday": "8:30AM-5PM"
      },
      "reviews_per_score": {
        "1": 1,
        "2": 0,
        "3": 0,
        "4": 0,
        "5": 6
      },
      "business_status": "OPERATIONAL",
      "is_verified": true,
      "is_claimed": true
    },
    {
      "slug": "wayne-rivers-cpa",
      "name": "Wayne Rivers, CPA",
      "category": "Tax preparation service",
      "phone": "+1 360-687-3089",
      "site": "https://www.wayneriverscpa.com/",
      "address": "616 E Main St, Battle Ground, WA 98604",
      "latitude": 45.7810826,
      "longitude": -122.5304532,
      "rating": 4.7,
      "reviews": 62,
      "logo": "https://lh4.googleusercontent.com/-H3nwFlNRIDY/AAAAAAAAAAI/AAAAAAAAAAA/m2ci8VpkpHk/s44-p-k-no-ns-nd/photo.jpg",
      "photo": "https://lh3.googleusercontent.com/gps-cs-s/APNQkAHjykQtGHaJdeWHs0pEFCNZwKxmXxyNkeqM-PUEdn4nTeO-z_NxrTagItHYaDChkk-yd_xRcR-Lfw-2XJFeY6u0Nn75WnTPVbnoA5FaY-Mx7J9dRGMTJV2H9KtbBSbVSHTULDjVFEkuWpFn=w800-h500-k-no",
      "working_hours": {
        "Friday": "8:30AM-5PM",
        "Monday": "8:30AM-5PM",
        "Saturday": "Closed",
        "Sunday": "Closed",
        "Thursday": "8:30AM-5PM",
        "Tuesday": "8:30AM-5PM",
        "Wednesday": "8:30AM-5PM"
      },
      "reviews_per_score": {
        "1": 3,
        "2": 2,
        "3": 0,
        "4": 1,
        "5": 56
      },
      "business_status": "OPERATIONAL",
      "is_verified": true,
      "is_claimed": true
    },
    {
      "slug": "legacy-accounting-and-financial-services-pllc",
      "name": "Legacy Accounting and Financial Services, PLLC",
      "category": "Accountant",
      "phone": "+1 360-597-0400",
      "site": "http://legacyaccountingfinancial.com/",
      "address": "10637 NE Coxley Dr Suite 106, Vancouver, WA 98662",
      "latitude": 45.6621959,
      "longitude": -122.5642439,
      "rating": 5,
      "reviews": 7,
      "logo": "https://lh6.googleusercontent.com/-pZBb_0vZgmg/AAAAAAAAAAI/AAAAAAAAAAA/WZ5c7i2JmCs/s44-p-k-no-ns-nd/photo.jpg",
      "photo": "https://lh3.googleusercontent.com/gps-cs-s/APNQkAGTKm-R2peZhtISp94aMtw462t0kji07F0RMY0upnWNcx6NdFAtn7fipkc-a-h0K9QZvWb5E3nYyPM9fMnxgRwfew5wEO0bosTvrllzCBS6d1-LnqoTdgn3ByJbybp5avP9lpKc5Q=w800-h500-k-no",
      "working_hours": {
        "Friday": "9AM-5PM",
        "Monday": "9AM-5PM",
        "Saturday": "Closed",
        "Sunday": "Closed",
        "Thursday": "9AM-5PM",
        "Tuesday": "9AM-5PM",
        "Wednesday": "9AM-5PM"
      },
      "reviews_per_score": {
        "1": 0,
        "2": 0,
        "3": 0,
        "4": 0,
        "5": 7
      },
      "business_status": "OPERATIONAL",
      "is_verified": true,
      "is_claimed": true
    },
    {
      "slug": "integrated-tax-services",
      "name": "Integrated Tax Services",
      "category": "Accounting firm",
      "phone": "+1 360-695-1120",
      "site": "http://its-taxes.com/",
      "address": "275 W 3rd St Suite 500, Vancouver, WA 98660",
      "latitude": 45.623182,
      "longitude": -122.67326969999999,
      "rating": 5,
      "reviews": 2,
      "logo": "https://lh6.googleusercontent.com/-dmuqVLZHEMk/AAAAAAAAAAI/AAAAAAAAAAA/ec6h7JZOzz8/s44-p-k-no-ns-nd/photo.jpg",
      "photo": "https://lh3.googleusercontent.com/gps-cs-s/APNQkAEa5AJRyY56XbQR7WfTmp5stdAEqNae6AlNl7wNXjNGofv5d53l-bKADQj4qM1BHzXbczNi7yNVfHsOUyjtIjQVQzJLHQaHx84a5a2qY1jQuzfv_liImdIJpRH63Xhl3gcfyKCudw=w800-h500-k-no",
      "working_hours": {
        "Friday": "8AM-2PM",
        "Monday": "8AM-5PM",
        "Saturday": "Closed",
        "Sunday": "Closed",
        "Thursday": "8AM-5PM",
        "Tuesday": "8AM-5PM",
        "Wednesday": "8AM-5PM"
      },
      "reviews_per_score": {
        "1": 0,
        "2": 0,
        "3": 0,
        "4": 0,
        "5": 2
      },
      "business_status": "OPERATIONAL",
      "is_verified": true,
      "is_claimed": true
    },
    {
      "slug": "wilen-and-associates",
      "name": "Wilen & Associates",
      "category": "Tax preparation service",
      "phone": "+1 360-695-9818",
      "site": "",
      "address": "10811 NE 26th St, Vancouver, WA 98684",
      "latitude": 45.6410407,
      "longitude": -122.56109649999999,
      "rating": 4.4,
      "reviews": 12,
      "logo": "",
      "photo": "https://streetviewpixels-pa.googleapis.com/v1/thumbnail?panoid=Q8GzWXLG8ZN_uzAe_7x0Aw&cb_client=search.gws-prod.gps&w=800&h=500&yaw=230.26189&pitch=0&thumbfov=100",
      "working_hours": {
        "Friday": "Open 24 hours",
        "Monday": "Open 24 hours",
        "Saturday": "Open 24 hours",
        "Sunday": "Open 24 hours",
        "Thursday": "Open 24 hours",
        "Tuesday": "Open 24 hours",
        "Wednesday": "Open 24 hours"
      },
      "reviews_per_score": {
        "1": 1,
        "2": 1,
        "3": 0,
        "4": 0,
        "5": 10
      },
      "business_status": "OPERATIONAL",
      "is_verified": false,
      "is_claimed": false
    },
    {
      "slug": "nationwide-virtual-accounting-and-tax",
      "name": "Nationwide Virtual Accounting & Tax",
      "category": "Accountant",
      "phone": "+1 360-200-5706",
      "site": "http://thetaxhome.com/",
      "address": "8703 NE 97th Ct, Vancouver, WA 98662",
      "latitude": 45.6852387,
      "longitude": -122.5727915,
      "rating": 4.7,
      "reviews": 23,
      "logo": "https://lh3.googleusercontent.com/-EGD9-I4vdTA/AAAAAAAAAAI/AAAAAAAAAAA/0RdTlPru6rw/s44-p-k-no-ns-nd/photo.jpg",
      "photo": "https://lh3.googleusercontent.com/gps-cs-s/APNQkAEmfYYk2nxb25zWZcy5oN3rPhxsYGv7Y8CNenx_gjJ5kpPy44ZDbiWTEDxGzR34NTM-UiKM7e1nIYI1j9duVnyo1w-MBsT8ssFtvbJnvvIG64U3ad0RXow5bMVjTdaWEpWMrN-b=w800-h500-k-no",
      "working_hours": {
        "Friday": "9AM-6PM",
        "Monday": "9AM-6PM",
        "Saturday": "10AM-2PM",
        "Sunday": "Closed",
        "Thursday": "9AM-6PM",
        "Tuesday": "9AM-6PM",
        "Wednesday": "9AM-6PM"
      },
      "reviews_per_score": {
        "1": 2,
        "2": 0,
        "3": 0,
        "4": 0,
        "5": 21
      },
      "business_status": "OPERATIONAL",
      "is_verified": true,
      "is_claimed": true
    }
  ]
}