{
  "city": "Reno",
  "state": "Nevada",
  "state_code": "NV",
  "city_slug": "reno",
  "state_slug": "nevada",
  "firm_count": 20,
  "firms": [
    {
      "slug": "stone-ridge-cpas",
      "name": "Stone Ridge CPAs",
      "category": "Certified public accountant",
      "phone": "+1 775-826-9400",
      "site": "http://www.renocpa.net/",
      "address": "5865 Tyrone Rd Ste 101, Reno, NV 89502",
      "latitude": 39.4744235,
      "longitude": -119.7747911,
      "rating": 5,
      "reviews": 66,
      "logo": "https://lh4.googleusercontent.com/-VxXUJlvL_Qs/AAAAAAAAAAI/AAAAAAAAAAA/_7zcb58iZI0/s44-p-k-no-ns-nd/photo.jpg",
      "photo": "https://lh3.googleusercontent.com/gps-cs-s/APNQkAGkTtJpiSCY3Eub-LEix460ZU2dAZIgogwgWUkm2WVaOpsMJzfU7nCVxX4lLFF-h9kr8jwCo8ZvL2UpWB2NncN92g3D5uBtF5XZNN_bvpdk8P4co12FC0_YYI3-LsfonaUQ_Wa2zTXPRZ2i=w800-h500-k-no",
      "working_hours": {
        "Friday": "9AM-5PM",
        "Monday": "9AM-5PM",
        "Saturday": "Closed",
        "Sunday": "Closed",
        "Thursday": "9AM-5PM",
        "Tuesday": "9AM-5PM",
        "Wednesday": "9AM-5PM"
      },
      "reviews_per_score": {
        "1": 0,
        "2": 0,
        "3": 0,
        "4": 2,
        "5": 64
      },
      "business_status": "OPERATIONAL",
      "is_verified": true,
      "is_claimed": true
    },
    {
      "slug": "belle-business-services",
      "name": "Belle Business Services",
      "category": "Accountant",
      "phone": "+1 775-525-1829",
      "site": "http://www.belle.cpa/",
      "address": "36 Stewart St 2nd Floor, Reno, NV 89501",
      "latitude": 39.5209645,
      "longitude": -119.8095189,
      "rating": 4.4,
      "reviews": 35,
      "logo": "https://lh6.googleusercontent.com/-SOD85CFoSHo/AAAAAAAAAAI/AAAAAAAAAAA/RQuK1cmLj78/s44-p-k-no-ns-nd/photo.jpg",
      "photo": "https://streetviewpixels-pa.googleapis.com/v1/thumbnail?panoid=pzEo9rDoaMSswpFZwLHYBQ&cb_client=search.gws-prod.gps&w=800&h=500&yaw=160.24219&pitch=0&thumbfov=100",
      "working_hours": {
        "Monday": "Closed",
        "Tuesday": "Closed",
        "Wednesday": "Closed",
        "Thursday": "Closed",
        "Friday": "Closed",
        "Saturday": "Closed",
        "Sunday": "Closed"
      },
      "reviews_per_score": {
        "1": 4,
        "2": 2,
        "3": 0,
        "4": 0,
        "5": 29
      },
      "business_status": "OPERATIONAL",
      "is_verified": true,
      "is_claimed": true
    },
    {
      "slug": "excelsis-accounting-group",
      "name": "Excelsis Accounting Group",
      "category": "Certified public accountant",
      "phone": "+1 775-332-4200",
      "site": "https://www.excelsisaccounting.com/",
      "address": "5335 Kietzke Ln #110, Reno, NV 89511",
      "latitude": 39.4694341,
      "longitude": -119.7925466,
      "rating": 4.7,
      "reviews": 38,
      "logo": "https://lh4.googleusercontent.com/-y-QBw8lsO1w/AAAAAAAAAAI/AAAAAAAAAAA/pFaX-fsMB-o/s44-p-k-no-ns-nd/photo.jpg",
      "photo": "https://lh3.googleusercontent.com/gps-cs-s/APNQkAFKgsXWXIwPXrZpYXb99QyidU53CtBn4M-fs0quI0mzLVCpFMDtzp3jFUOHfjvnibf6tLfRml3Tw3fTUqb5lAdjB9mYi97HCxWAuKTijTvyves6VlcpSACDBV6nUENdURw9VsJai9Nuvwz9=w800-h500-k-no",
      "working_hours": {
        "Friday": "8AM-5PM",
        "Monday": "8AM-5PM",
        "Saturday": "Closed",
        "Sunday": "Closed",
        "Thursday": "8AM-5PM",
        "Tuesday": "8AM-5PM",
        "Wednesday": "8AM-5PM"
      },
      "reviews_per_score": {
        "1": 2,
        "2": 0,
        "3": 0,
        "4": 2,
        "5": 34
      },
      "business_status": "OPERATIONAL",
      "is_verified": true,
      "is_claimed": true
    },
    {
      "slug": "mark-robertson-cpa",
      "name": "Mark Robertson CPA",
      "category": "Tax preparation service",
      "phone": "+1 775-825-5522",
      "site": "http://www.renocpafirm.com/",
      "address": "9190 Double Diamond Pkwy #128, Reno, NV 89521",
      "latitude": 39.446307,
      "longitude": -119.7482184,
      "rating": 4.4,
      "reviews": 7,
      "logo": "https://lh4.googleusercontent.com/-nb_fdjYKHL4/AAAAAAAAAAI/AAAAAAAAAAA/W3PN3xpbrN8/s44-p-k-no-ns-nd/photo.jpg",
      "photo": "https://streetviewpixels-pa.googleapis.com/v1/thumbnail?panoid=ILoQ0KRvAwQ_j5ROjrQ5RA&cb_client=search.gws-prod.gps&w=800&h=500&yaw=258.51086&pitch=0&thumbfov=100",
      "working_hours": {
        "Friday": "9AM-5PM",
        "Monday": "9AM-5PM",
        "Saturday": "Closed",
        "Sunday": "Closed",
        "Thursday": "9AM-5PM",
        "Tuesday": "9AM-5PM",
        "Wednesday": "9AM-5PM"
      },
      "reviews_per_score": {
        "1": 1,
        "2": 0,
        "3": 0,
        "4": 0,
        "5": 6
      },
      "business_status": "OPERATIONAL",
      "is_verified": true,
      "is_claimed": true
    },
    {
      "slug": "berge-and-company-cpa",
      "name": "Berge & Company CPA",
      "category": "Tax preparation service",
      "phone": "+1 775-298-6693",
      "site": "",
      "address": "223 Marsh Ave, Reno, NV 89509",
      "latitude": 39.5192474,
      "longitude": -119.8132799,
      "rating": 4.5,
      "reviews": 39,
      "logo": "https://lh4.googleusercontent.com/-AW0LMpDf6L0/AAAAAAAAAAI/AAAAAAAAAAA/Z2WXIINDof8/s44-p-k-no-ns-nd/photo.jpg",
      "photo": "https://streetviewpixels-pa.googleapis.com/v1/thumbnail?panoid=fZcx9KLDQ_mFW6mkwGJ4NQ&cb_client=search.gws-prod.gps&w=800&h=500&yaw=67.09997&pitch=0&thumbfov=100",
      "working_hours": {
        "Monday": "Closed",
        "Tuesday": "Closed",
        "Wednesday": "Closed",
        "Thursday": "Closed",
        "Friday": "Closed",
        "Saturday": "Closed",
        "Sunday": "Closed"
      },
      "reviews_per_score": {
        "1": 5,
        "2": 0,
        "3": 0,
        "4": 0,
        "5": 34
      },
      "business_status": "OPERATIONAL",
      "is_verified": true,
      "is_claimed": true
    },
    {
      "slug": "michael-mellberg-cpa",
      "name": "Michael Mellberg CPA",
      "category": "Certified public accountant",
      "phone": "+1 775-323-8131",
      "site": "http://mellbergcpa.com/",
      "address": "1755 E Plumb Ln # 216, Reno, NV 89502",
      "latitude": 39.50674,
      "longitude": -119.77913199999999,
      "rating": 4.7,
      "reviews": 13,
      "logo": "https://lh3.googleusercontent.com/-DgotQ2JDF9E/AAAAAAAAAAI/AAAAAAAAAAA/z0EzsEOZM3s/s44-p-k-no-ns-nd/photo.jpg",
      "photo": "https://streetviewpixels-pa.googleapis.com/v1/thumbnail?panoid=L0-119HP2iVPD4AmbJUe4A&cb_client=search.gws-prod.gps&w=800&h=500&yaw=101.32683&pitch=0&thumbfov=100",
      "working_hours": {
        "Friday": "Closed",
        "Monday": "9AM-5PM",
        "Saturday": "Closed",
        "Sunday": "Closed",
        "Thursday": "9AM-5PM",
        "Tuesday": "9AM-5PM",
        "Wednesday": "9AM-5PM"
      },
      "reviews_per_score": {
        "1": 1,
        "2": 0,
        "3": 0,
        "4": 0,
        "5": 12
      },
      "business_status": "OPERATIONAL",
      "is_verified": true,
      "is_claimed": true
    },
    {
      "slug": "forbush-cpas",
      "name": "Forbush CPAs",
      "category": "Accountant",
      "phone": "+1 775-337-6001",
      "site": "http://forbushcpa.com/",
      "address": "5490 Longley Ln ste a, Reno, NV 89511",
      "latitude": 39.469612,
      "longitude": -119.76580659999999,
      "rating": 4.2,
      "reviews": 10,
      "logo": "https://lh4.googleusercontent.com/-j4n2zdDQowE/AAAAAAAAAAI/AAAAAAAAAAA/-H_axbAW-3g/s44-p-k-no-ns-nd/photo.jpg",
      "photo": "https://lh3.googleusercontent.com/gps-cs-s/APNQkAGSfGlxnWaGVZhkb9DUuPbfHIOp0uhsQPCYgonkXO2qv7YTVS8DuxxP3wg8pQndQ3kWuytO5MizJdPyAP_-8K39Lecx9d5zRqpKQKgzOAN9ld-CZclbYgVcyt5srClSeJhPfKzeiw=w800-h500-k-no",
      "working_hours": {
        "Friday": "8AM-5PM",
        "Monday": "8AM-5PM",
        "Saturday": "Closed",
        "Sunday": "Closed",
        "Thursday": "8AM-5PM",
        "Tuesday": "8AM-5PM",
        "Wednesday": "8AM-5PM"
      },
      "reviews_per_score": {
        "1": 2,
        "2": 0,
        "3": 0,
        "4": 0,
        "5": 8
      },
      "business_status": "OPERATIONAL",
      "is_verified": true,
      "is_claimed": true
    },
    {
      "slug": "michael-j-dobrowski-cpa-llc",
      "name": "Michael J. Dobrowski, CPA, LLC",
      "category": "Certified public accountant",
      "phone": "+1 775-329-0843",
      "site": "http://renotaxservices.com/",
      "address": "6580 S McCarran Blvd suite d 2, Reno, NV 89509",
      "latitude": 39.4756971,
      "longitude": -119.7989767,
      "rating": 5,
      "reviews": 1,
      "logo": "",
      "photo": "https://streetviewpixels-pa.googleapis.com/v1/thumbnail?panoid=hApbDk66NzUn8iHi5dLgLg&cb_client=search.gws-prod.gps&w=800&h=500&yaw=322.8466&pitch=0&thumbfov=100",
      "working_hours": {
        "Friday": "8AM-4:30PM",
        "Monday": "8AM-4:30PM",
        "Saturday": "Closed",
        "Sunday": "Closed",
        "Thursday": "8AM-4:30PM",
        "Tuesday": "8AM-4:30PM",
        "Wednesday": "8AM-4:30PM"
      },
      "reviews_per_score": {
        "1": 0,
        "2": 0,
        "3": 0,
        "4": 0,
        "5": 1
      },
      "business_status": "OPERATIONAL",
      "is_verified": false,
      "is_claimed": false
    },
    {
      "slug": "leon-jaferian-cpa",
      "name": "Leon Jaferian, CPA",
      "category": "Certified public accountant",
      "phone": "+1 775-826-8555",
      "site": "http://www.jaferiancpa.com/",
      "address": "6100 Plumas St #202, Reno, NV 89519",
      "latitude": 39.472710899999996,
      "longitude": -119.8107723,
      "rating": 4.5,
      "reviews": 8,
      "logo": "https://lh6.googleusercontent.com/-QAdjnUBQK_s/AAAAAAAAAAI/AAAAAAAAAAA/Dcr7IO0qJs8/s44-p-k-no-ns-nd/photo.jpg",
      "photo": "https://streetviewpixels-pa.googleapis.com/v1/thumbnail?panoid=yIIgkoVSc7OmYGs0goGkKg&cb_client=search.gws-prod.gps&w=800&h=500&yaw=352.7266&pitch=0&thumbfov=100",
      "working_hours": {
        "Friday": "8AM-4AM",
        "Monday": "8AM-4:30PM",
        "Saturday": "9AM-1PM",
        "Sunday": "Closed",
        "Thursday": "12-4:30AM, 8AM-4:30PM",
        "Tuesday": "8PM-12AM",
        "Wednesday": "Open 24 hours"
      },
      "reviews_per_score": {
        "1": 1,
        "2": 0,
        "3": 0,
        "4": 0,
        "5": 7
      },
      "business_status": "OPERATIONAL",
      "is_verified": true,
      "is_claimed": true
    },
    {
      "slug": "keystone-cpas",
      "name": "Keystone CPAs",
      "category": "Accounting firm",
      "phone": "+1 775-786-4900",
      "site": "https://www.keystone.cpa/",
      "address": "401 Ryland St, Reno, NV 89502",
      "latitude": 39.5239908,
      "longitude": -119.80598619999999,
      "rating": 3.7,
      "reviews": 3,
      "logo": "https://lh5.googleusercontent.com/-DapYRjG1zqw/AAAAAAAAAAI/AAAAAAAAAAA/h3icYA44O6I/s44-p-k-no-ns-nd/photo.jpg",
      "photo": "https://lh3.googleusercontent.com/gps-cs-s/APNQkAF19BRYsnbK5mCkzb6UIHlSd6823PxMCG-FClcfs1frBPcBZRHxmH_EC-mvINusBAQ-VVo-oHFk706g4b6OXZvwpWitervHkWj-qwohH2Az8Gswp3vFzG3C1tDXWQrUusjhXF97zbo80hTw=w800-h500-k-no",
      "working_hours": {
        "Friday": "8AM-5PM",
        "Monday": "8AM-5PM",
        "Saturday": "Closed",
        "Sunday": "Closed",
        "Thursday": "8AM-5PM",
        "Tuesday": "8AM-5PM",
        "Wednesday": "8AM-5PM"
      },
      "reviews_per_score": {
        "1": 1,
        "2": 0,
        "3": 0,
        "4": 0,
        "5": 2
      },
      "business_status": "OPERATIONAL",
      "is_verified": true,
      "is_claimed": true
    },
    {
      "slug": "rand-cpas",
      "name": "Rand CPA's",
      "category": "Certified public accountant",
      "phone": "+1 775-525-5291",
      "site": "https://www.randcpa.com/",
      "address": "9190 Double Diamond Pkwy, Reno, NV 89521",
      "latitude": 39.446307,
      "longitude": -119.7482184,
      "rating": 4.6,
      "reviews": 19,
      "logo": "https://lh3.googleusercontent.com/-7OamM-pCG_M/AAAAAAAAAAI/AAAAAAAAAAA/3n7Vy3pY0k8/s44-p-k-no-ns-nd/photo.jpg",
      "photo": "https://lh3.googleusercontent.com/gps-cs-s/APNQkAE0oc8b99H2OxhPKi78JnJX8fjhPRpVHKoyGpCCHb4TmAfqXslQytwoAMqUiuAYjrPknvicFTfQwboOFFeI4dpFdAUo-F0oK_zmjWG7sPwd5kd3aBKG03ljxUW-8RL6Nten4iTAQA=w800-h500-k-no",
      "working_hours": {
        "Friday": "8AM-5PM",
        "Monday": "8AM-5PM",
        "Saturday": "Closed",
        "Sunday": "Closed",
        "Thursday": "8AM-5PM",
        "Tuesday": "8AM-5PM",
        "Wednesday": "8AM-5PM"
      },
      "reviews_per_score": {
        "1": 2,
        "2": 0,
        "3": 0,
        "4": 0,
        "5": 17
      },
      "business_status": "OPERATIONAL",
      "is_verified": true,
      "is_claimed": true
    },
    {
      "slug": "evans-nelson-and-company-cpas",
      "name": "Evans Nelson & Company CPAs",
      "category": "Accountant",
      "phone": "+1 775-825-6008",
      "site": "http://encpas.com/",
      "address": "160 W Huffaker Ln, Reno, NV 89511",
      "latitude": 39.454655599999995,
      "longitude": -119.78053949999999,
      "rating": 3.2,
      "reviews": 10,
      "logo": "https://lh4.googleusercontent.com/-T3v_Dvnw1Eg/AAAAAAAAAAI/AAAAAAAAAAA/KcdPteywZds/s44-p-k-no-ns-nd/photo.jpg",
      "photo": "https://lh3.googleusercontent.com/gps-cs-s/APNQkAFh8314gNXjq08pbrYW3GveS1Gz3C72ZlMxk-eIK9hwEMxgwA5qqvFAgc4D3Xyk58H8T-VvHSYr-Po3RQjeYmU9vRw9taYRV10SYp3vuvFJQ0P_Asr9laRiy50Y-3FLpeb4KwVrHA=w800-h500-k-no",
      "working_hours": {
        "Friday": "8AM-12PM, 1-5PM",
        "Monday": "8AM-12PM, 1-5PM",
        "Saturday": "Closed",
        "Sunday": "Closed",
        "Thursday": "8AM-12PM, 1-5PM",
        "Tuesday": "8AM-12PM, 1-5PM",
        "Wednesday": "8AM-12PM, 1-5PM"
      },
      "reviews_per_score": {
        "1": 4,
        "2": 0,
        "3": 1,
        "4": 0,
        "5": 5
      },
      "business_status": "OPERATIONAL",
      "is_verified": true,
      "is_claimed": true
    },
    {
      "slug": "eide-bailly",
      "name": "Eide Bailly",
      "category": "Accounting firm",
      "phone": "+1 775-689-9100",
      "site": "https://www.eidebailly.com/locations/reno",
      "address": "5441 Kietzke Ln Ste. 150, Reno, NV 89511",
      "latitude": 39.464909399999996,
      "longitude": -119.790613,
      "rating": 5,
      "reviews": 9,
      "logo": "https://lh5.googleusercontent.com/-NpMxGiKnhWA/AAAAAAAAAAI/AAAAAAAAAAA/NVNd9fFPoTc/s44-p-k-no-ns-nd/photo.jpg",
      "photo": "https://streetviewpixels-pa.googleapis.com/v1/thumbnail?panoid=-nhevwukjEpH0r8MTmBLpg&cb_client=search.gws-prod.gps&w=800&h=500&yaw=155.08325&pitch=0&thumbfov=100",
      "working_hours": {
        "Friday": "8AM-5PM",
        "Monday": "8AM-5PM",
        "Saturday": "Closed",
        "Sunday": "Closed",
        "Thursday": "8AM-5PM",
        "Tuesday": "8AM-5PM",
        "Wednesday": "8AM-5PM"
      },
      "reviews_per_score": {
        "1": 0,
        "2": 0,
        "3": 0,
        "4": 0,
        "5": 9
      },
      "business_status": "OPERATIONAL",
      "is_verified": true,
      "is_claimed": true
    },
    {
      "slug": "harger-cpa-inc",
      "name": "Harger CPA, inc.",
      "category": "Tax preparation service",
      "phone": "+1 775-393-9119",
      "site": "http://hargertaxcpa.com/",
      "address": "9805 Double R Blvd, Reno, NV 89511",
      "latitude": 39.442813099999995,
      "longitude": -119.7610181,
      "rating": 4.7,
      "reviews": 20,
      "logo": "https://lh6.googleusercontent.com/-GZGuVvhFbjw/AAAAAAAAAAI/AAAAAAAAAAA/4X9Z-NqrOoY/s44-p-k-no-ns-nd/photo.jpg",
      "photo": "https://streetviewpixels-pa.googleapis.com/v1/thumbnail?panoid=dHdca0ulP8Sp4JhV3QQKbA&cb_client=search.gws-prod.gps&w=800&h=500&yaw=257.5958&pitch=0&thumbfov=100",
      "working_hours": {
        "Friday": "8AM-5PM",
        "Monday": "8AM-5PM",
        "Saturday": "Closed",
        "Sunday": "Closed",
        "Thursday": "8AM-5PM",
        "Tuesday": "8AM-5PM",
        "Wednesday": "8AM-5PM"
      },
      "reviews_per_score": {
        "1": 1,
        "2": 0,
        "3": 0,
        "4": 2,
        "5": 17
      },
      "business_status": "OPERATIONAL",
      "is_verified": true,
      "is_claimed": true
    },
    {
      "slug": "barnard-vogler-and-co",
      "name": "Barnard Vogler & Co",
      "category": "Accounting firm",
      "phone": "+1 775-786-6141",
      "site": "http://bvcocpas.com/",
      "address": "100 W Liberty St # 1100, Reno, NV 89501",
      "latitude": 39.5211586,
      "longitude": -119.81291279999999,
      "rating": 5,
      "reviews": 2,
      "logo": "https://lh5.googleusercontent.com/-HltJbkRkY9s/AAAAAAAAAAI/AAAAAAAAAAA/_CSyQ5y-BIg/s44-p-k-no-ns-nd/photo.jpg",
      "photo": "https://streetviewpixels-pa.googleapis.com/v1/thumbnail?panoid=XjKeyDMvLLCrRtE3d-zW8w&cb_client=search.gws-prod.gps&w=800&h=500&yaw=82.933365&pitch=0&thumbfov=100",
      "working_hours": {
        "Friday": "8AM-5PM",
        "Monday": "8AM-5PM",
        "Saturday": "Closed",
        "Sunday": "Closed",
        "Thursday": "8AM-5PM",
        "Tuesday": "8AM-5PM",
        "Wednesday": "8AM-5PM"
      },
      "reviews_per_score": {
        "1": 0,
        "2": 0,
        "3": 0,
        "4": 0,
        "5": 2
      },
      "business_status": "OPERATIONAL",
      "is_verified": true,
      "is_claimed": true
    },
    {
      "slug": "albright-and-associates-ltd",
      "name": "Albright & Associates, Ltd.",
      "category": "Accountant",
      "phone": "+1 775-826-5432",
      "site": "http://www.albrightcpas.com/",
      "address": "6121 Lakeside Dr #100, Reno, NV 89511",
      "latitude": 39.4725186,
      "longitude": -119.80825109999999,
      "rating": 5,
      "reviews": 1,
      "logo": "https://lh4.googleusercontent.com/-1IbzUOIv9ys/AAAAAAAAAAI/AAAAAAAAAAA/AMUXNN9qleA/s44-p-k-no-ns-nd/photo.jpg",
      "photo": "https://lh3.googleusercontent.com/gps-cs-s/APNQkAG84qLIaWgQWEsgky21KCkEq4FL0QZHTMyLNPfq6pOUR8o6aO_ya1N0s_XJdOWhhOz3v386bn4WbRiI5c-61I38r_-gZWc8BbipW-5-C7QnK3XTdOuy6NTkgbuxZFHgemkPWXtNSQ=w800-h500-k-no",
      "working_hours": {
        "Friday": "8AM-5PM",
        "Monday": "8AM-5PM",
        "Saturday": "Closed",
        "Sunday": "Closed",
        "Thursday": "8AM-5PM",
        "Tuesday": "8AM-5PM",
        "Wednesday": "8AM-5PM"
      },
      "reviews_per_score": {
        "1": 0,
        "2": 0,
        "3": 0,
        "4": 0,
        "5": 1
      },
      "business_status": "OPERATIONAL",
      "is_verified": true,
      "is_claimed": true
    },
    {
      "slug": "ludmila-cpa-inc",
      "name": "Ludmila CPA Inc",
      "category": "Accounting firm",
      "phone": "+1 775-636-6601",
      "site": "https://ludmilacpa.com/",
      "address": "18 Stewart St, Reno, NV 89501",
      "latitude": 39.520891299999995,
      "longitude": -119.81002699999999,
      "rating": 4.5,
      "reviews": 6,
      "logo": "https://lh6.googleusercontent.com/-QelFCVPtvzI/AAAAAAAAAAI/AAAAAAAAAAA/9Mhiityr7Do/s44-p-k-no-ns-nd/photo.jpg",
      "photo": "https://streetviewpixels-pa.googleapis.com/v1/thumbnail?panoid=q4NVcoEWgMObcU2Grk-ZVg&cb_client=search.gws-prod.gps&w=800&h=500&yaw=187.98842&pitch=0&thumbfov=100",
      "working_hours": {
        "Friday": "9AM-5PM",
        "Monday": "9AM-5PM",
        "Saturday": "Closed",
        "Sunday": "Closed",
        "Thursday": "9AM-5PM",
        "Tuesday": "9AM-5PM",
        "Wednesday": "9AM-5PM"
      },
      "reviews_per_score": {
        "1": 0,
        "2": 1,
        "3": 0,
        "4": 0,
        "5": 5
      },
      "business_status": "OPERATIONAL",
      "is_verified": true,
      "is_claimed": true
    },
    {
      "slug": "ray-melvin-s-cpa",
      "name": "Ray Melvin S CPA",
      "category": "Accountant",
      "phone": "+1 775-322-0671",
      "site": "http://www.melvinraycpa.com/",
      "address": "6900 S McCarran Blvd # 1040, Reno, NV 89509",
      "latitude": 39.4758608,
      "longitude": -119.8067153,
      "rating": 5,
      "reviews": 2,
      "logo": "",
      "photo": "https://streetviewpixels-pa.googleapis.com/v1/thumbnail?panoid=lLKAMhP-XWvLRq7Bdb8MlQ&cb_client=search.gws-prod.gps&w=800&h=500&yaw=189.48767&pitch=0&thumbfov=100",
      "working_hours": {
        "Friday": "9AM-5PM",
        "Monday": "9AM-5PM",
        "Saturday": "Closed",
        "Sunday": "Closed",
        "Thursday": "9AM-5PM",
        "Tuesday": "9AM-5PM",
        "Wednesday": "9AM-5PM"
      },
      "reviews_per_score": {
        "1": 0,
        "2": 0,
        "3": 0,
        "4": 0,
        "5": 2
      },
      "business_status": "OPERATIONAL",
      "is_verified": false,
      "is_claimed": false
    },
    {
      "slug": "consulting-tax-group",
      "name": "Consulting Tax Group",
      "category": "Tax preparation service",
      "phone": "+1 775-324-6444",
      "site": "http://www.taxgroupnv.com/",
      "address": "5470 Kietzke Ln #300, Reno, NV 89511",
      "latitude": 39.464943999999996,
      "longitude": -119.789192,
      "rating": 3.3,
      "reviews": 7,
      "logo": "https://lh4.googleusercontent.com/-Qnz6dapiGAg/AAAAAAAAAAI/AAAAAAAAAAA/JQZdh0olgTY/s44-p-k-no-ns-nd/photo.jpg",
      "photo": "https://streetviewpixels-pa.googleapis.com/v1/thumbnail?panoid=vuVZ8Ju2Gl0n_Cf0tOQkcw&cb_client=search.gws-prod.gps&w=800&h=500&yaw=148.45523&pitch=0&thumbfov=100",
      "working_hours": {
        "Friday": "9AM-6PM",
        "Monday": "9AM-6PM",
        "Saturday": "Closed",
        "Sunday": "Closed",
        "Thursday": "9AM-6PM",
        "Tuesday": "9AM-6PM",
        "Wednesday": "9AM-6PM"
      },
      "reviews_per_score": {
        "1": 3,
        "2": 0,
        "3": 0,
        "4": 0,
        "5": 4
      },
      "business_status": "OPERATIONAL",
      "is_verified": true,
      "is_claimed": true
    },
    {
      "slug": "di-pietro-and-thornton",
      "name": "Di Pietro & Thornton",
      "category": "Accountant",
      "phone": "+1 775-825-1040",
      "site": "http://www.dipietro-thornton.com/",
      "address": "9550 Prototype Ct #101, Reno, NV 89521",
      "latitude": 39.4436489,
      "longitude": -119.7633985,
      "rating": 5,
      "reviews": 2,
      "logo": "",
      "photo": "https://streetviewpixels-pa.googleapis.com/v1/thumbnail?panoid=5598_v1lFNP2zKTrX5LX7A&cb_client=search.gws-prod.gps&w=800&h=500&yaw=208.19463&pitch=0&thumbfov=100",
      "working_hours": {
        "Friday": "9AM-5PM",
        "Monday": "9AM-5PM",
        "Saturday": "Closed",
        "Sunday": "Closed",
        "Thursday": "9AM-5PM",
        "Tuesday": "9AM-5PM",
        "Wednesday": "9AM-5PM"
      },
      "reviews_per_score": {
        "1": 0,
        "2": 0,
        "3": 0,
        "4": 0,
        "5": 2
      },
      "business_status": "OPERATIONAL",
      "is_verified": false,
      "is_claimed": false
    }
  ]
}