{
  "city": "Fishers",
  "state": "Indiana",
  "state_code": "IN",
  "city_slug": "fishers",
  "state_slug": "indiana",
  "firm_count": 20,
  "firms": [
    {
      "slug": "fishers-financials-llc",
      "name": "Fishers Financials LLC",
      "category": "Accounting firm",
      "phone": "+1 317-410-4532",
      "site": "https://fishersfinancials.com/",
      "address": "13914 E 116th St, Fishers, IN 46037",
      "latitude": 39.9581176,
      "longitude": -85.91470629999999,
      "rating": 5,
      "reviews": 52,
      "logo": "https://lh3.googleusercontent.com/-moSaIkNOQtk/AAAAAAAAAAI/AAAAAAAAAAA/i4uH1qlwMAg/s44-p-k-no-ns-nd/photo.jpg",
      "photo": "https://lh3.googleusercontent.com/gps-cs-s/APNQkAGgVBsLVFVVmUbil7tREO3r1qyID6nrb_IR-614e6_Z_Pus4GipSD3NqKIxQxmgOtL-JR6X2x4THg9vbqlh6KMPG9V9xiCLwr6KRbUKif6gPHx32113Ckq2gKDbUPbnEQLcxm7o0dnOlx96=w800-h500-k-no",
      "working_hours": {
        "Friday": "9AM-5PM",
        "Monday": "9AM-5PM",
        "Saturday": "10AM-3PM",
        "Sunday": "Closed",
        "Thursday": "9AM-5PM",
        "Tuesday": "9AM-5PM",
        "Wednesday": "9AM-5PM"
      },
      "reviews_per_score": {
        "1": 0,
        "2": 0,
        "3": 0,
        "4": 0,
        "5": 52
      },
      "business_status": "OPERATIONAL",
      "is_verified": true,
      "is_claimed": true
    },
    {
      "slug": "geist-cpa",
      "name": "Geist CPA",
      "category": "Certified public accountant",
      "phone": "+1 317-813-9979",
      "site": "http://www.geistcpa.com/",
      "address": "9924 Kings Horse Way, Fortville, IN 46040",
      "latitude": 39.9327368,
      "longitude": -85.90245949999999,
      "rating": 5,
      "reviews": 51,
      "logo": "https://lh5.googleusercontent.com/-J6Fr7TLMZo4/AAAAAAAAAAI/AAAAAAAAAAA/EWrqBg-NzPY/s44-p-k-no-ns-nd/photo.jpg",
      "photo": "https://streetviewpixels-pa.googleapis.com/v1/thumbnail?panoid=gCkyp3SlrpY_vg5emqIvFA&cb_client=search.gws-prod.gps&w=800&h=500&yaw=199.5111&pitch=0&thumbfov=100",
      "working_hours": {
        "Friday": "9AM-3PM",
        "Monday": "9AM-3PM",
        "Saturday": "Closed",
        "Sunday": "Closed",
        "Thursday": "9AM-3PM",
        "Tuesday": "9AM-3PM",
        "Wednesday": "9AM-3PM"
      },
      "reviews_per_score": {
        "1": 0,
        "2": 0,
        "3": 0,
        "4": 0,
        "5": 51
      },
      "business_status": "OPERATIONAL",
      "is_verified": true,
      "is_claimed": true
    },
    {
      "slug": "wagner-and-wetzel-cpa-group",
      "name": "Wagner & Wetzel CPA Group",
      "category": "Accountant",
      "phone": "+1 317-827-6915",
      "site": "http://www.wagnerwetzel.com/",
      "address": "11976 Fishers Crossing Dr, Fishers, IN 46038",
      "latitude": 39.9616393,
      "longitude": -86.0398325,
      "rating": 5,
      "reviews": 6,
      "logo": "https://lh4.googleusercontent.com/-ZNzY0FbBGQE/AAAAAAAAAAI/AAAAAAAAAAA/EzcnDMikf1Q/s44-p-k-no-ns-nd/photo.jpg",
      "photo": "https://streetviewpixels-pa.googleapis.com/v1/thumbnail?panoid=i9IGtEki7ZQbWvQP7mJ2bw&cb_client=search.gws-prod.gps&w=800&h=500&yaw=290.9347&pitch=0&thumbfov=100",
      "working_hours": {
        "Friday": "8:30AM-5PM",
        "Monday": "8:30AM-5PM",
        "Saturday": "Closed",
        "Sunday": "Closed",
        "Thursday": "8:30AM-5PM",
        "Tuesday": "8:30AM-5PM",
        "Wednesday": "8:30AM-5PM"
      },
      "reviews_per_score": {
        "1": 0,
        "2": 0,
        "3": 0,
        "4": 0,
        "5": 6
      },
      "business_status": "OPERATIONAL",
      "is_verified": true,
      "is_claimed": true
    },
    {
      "slug": "long-and-associates-pc",
      "name": "Long & Associates PC",
      "category": "Accounting firm",
      "phone": "+1 317-577-5975",
      "site": "http://www.longandassoc.com/",
      "address": "8388 E 116th St UNIT A, Fishers, IN 46038",
      "latitude": 39.9573211,
      "longitude": -86.0207446,
      "rating": 4.4,
      "reviews": 14,
      "logo": "",
      "photo": "https://streetviewpixels-pa.googleapis.com/v1/thumbnail?panoid=4EKIpMXHUuyIkB19JqVKWA&cb_client=search.gws-prod.gps&w=800&h=500&yaw=359.86844&pitch=0&thumbfov=100",
      "working_hours": {
        "Friday": "8AM-6PM",
        "Monday": "8AM-6PM",
        "Saturday": "Closed",
        "Sunday": "Closed",
        "Thursday": "8AM-6PM",
        "Tuesday": "8AM-6PM",
        "Wednesday": "8AM-6PM"
      },
      "reviews_per_score": {
        "1": 2,
        "2": 0,
        "3": 0,
        "4": 0,
        "5": 12
      },
      "business_status": "OPERATIONAL",
      "is_verified": false,
      "is_claimed": false
    },
    {
      "slug": "smith-cpa-group",
      "name": "Smith CPA Group",
      "category": "Accountant",
      "phone": "+1 317-857-0313",
      "site": "http://www.smithcpagroup.com/",
      "address": "12526 Promise Creek Ln Suite 320, Fishers, IN 46038",
      "latitude": 39.970389999999995,
      "longitude": -85.9739371,
      "rating": 5,
      "reviews": 1,
      "logo": "https://lh6.googleusercontent.com/-nf7uyJrFOAo/AAAAAAAAAAI/AAAAAAAAAAA/k1biAAFXlQQ/s44-p-k-no-ns-nd/photo.jpg",
      "photo": "https://lh3.googleusercontent.com/gps-cs-s/APNQkAGmoA-iEKtItpkW7nLCsZvDPctQ6p7AxxDTKql0Ln5M-PYCH7huDtYXTcfAIHQl-f9HFtfvV5Ijrd-7htF8D04VDWNzak7_YVf56CP0G-hAUKy1YtMJxesOe77TGp5rKCXzSGAZzw=w800-h500-k-no",
      "working_hours": {
        "Friday": "9AM-5PM",
        "Monday": "9AM-5PM",
        "Saturday": "Closed",
        "Sunday": "Closed",
        "Thursday": "9AM-5PM",
        "Tuesday": "9AM-5PM",
        "Wednesday": "9AM-5PM"
      },
      "reviews_per_score": {
        "1": 0,
        "2": 0,
        "3": 0,
        "4": 0,
        "5": 1
      },
      "business_status": "OPERATIONAL",
      "is_verified": true,
      "is_claimed": true
    },
    {
      "slug": "wright-accounting-group-llc",
      "name": "Wright Accounting Group, LLC",
      "category": "Accountant",
      "phone": "+1 317-507-1900",
      "site": "http://www.wrightaccountinggroup.com/",
      "address": "14074 Trade Center Dr #201, Fishers, IN 46038",
      "latitude": 39.991062299999996,
      "longitude": -86.0061526,
      "rating": 5,
      "reviews": 4,
      "logo": "https://lh5.googleusercontent.com/-xQS8JWqKV_M/AAAAAAAAAAI/AAAAAAAAAAA/e8FAbTEo8GU/s44-p-k-no-ns-nd/photo.jpg",
      "photo": "https://lh3.googleusercontent.com/gps-cs-s/APNQkAEAXmW-i54au-7XLvRWC7LzxuSt5XVs-zoLbTdlIOsXXO9g_xeh2NfB5elNGYFn6dFSlGuwhhevDw8z4sC1PFeJsXnFb8M4xQVqWz-xpFEIU7pjJ28F0F3qnDKJH16f8GwHNYnN=w800-h500-k-no",
      "working_hours": {
        "Friday": "9AM-4:30PM",
        "Monday": "9AM-4:30PM",
        "Saturday": "Closed",
        "Sunday": "Closed",
        "Thursday": "9AM-4:30PM",
        "Tuesday": "9AM-4:30PM",
        "Wednesday": "9AM-4:30PM"
      },
      "reviews_per_score": {
        "1": 0,
        "2": 0,
        "3": 0,
        "4": 0,
        "5": 4
      },
      "business_status": "OPERATIONAL",
      "is_verified": true,
      "is_claimed": true
    },
    {
      "slug": "nso-and-company-inc",
      "name": "NSO AND COMPANY, INC.",
      "category": "Accountant",
      "phone": "+1 317-588-3131",
      "site": "http://www.nsocpa.com/",
      "address": "8950 Fitness Ln, Fishers, IN 46037",
      "latitude": 39.9283218,
      "longitude": -86.0105229,
      "rating": 4.7,
      "reviews": 40,
      "logo": "https://lh5.googleusercontent.com/-wIcxh9U3U44/AAAAAAAAAAI/AAAAAAAAAAA/81NJl3QbJVU/s44-p-k-no-ns-nd/photo.jpg",
      "photo": "https://lh3.googleusercontent.com/gps-cs-s/APNQkAGf6h0d7GX_bMR28QU4cYg7l2Ctnm7uBBop6aTEwBCAESnNFYKAdur2KmzhmeONBBlwvWu_gg39GK1kzSMxWbxbyZtRHQEUKBR7X-gNlqgjNvteBxg2eN57_XujLlrEriNTQj6bVWSRX--S=w800-h500-k-no",
      "working_hours": {
        "Friday": "8:30AM-5PM",
        "Monday": "8:30AM-5PM",
        "Saturday": "Closed",
        "Sunday": "Closed",
        "Thursday": "8:30AM-5PM",
        "Tuesday": "8:30AM-5PM",
        "Wednesday": "8:30AM-5PM"
      },
      "reviews_per_score": {
        "1": 3,
        "2": 0,
        "3": 0,
        "4": 0,
        "5": 37
      },
      "business_status": "OPERATIONAL",
      "is_verified": true,
      "is_claimed": true
    },
    {
      "slug": "parker-todd-w-cpa",
      "name": "Parker Todd w CPA",
      "category": "Accountant",
      "phone": "+1 317-845-8844",
      "site": "",
      "address": "9740 Olympia Dr, Fishers, IN 46037",
      "latitude": 39.9286854,
      "longitude": -85.9829173,
      "rating": 4.2,
      "reviews": 5,
      "logo": "",
      "photo": "https://streetviewpixels-pa.googleapis.com/v1/thumbnail?panoid=pzLV7ARwiKCJZegPmsr2Xg&cb_client=search.gws-prod.gps&w=800&h=500&yaw=318.0795&pitch=0&thumbfov=100",
      "working_hours": {
        "Friday": "9AM-4PM",
        "Monday": "8AM-4PM",
        "Saturday": "Closed",
        "Sunday": "Closed",
        "Thursday": "8AM-4PM",
        "Tuesday": "8AM-4PM",
        "Wednesday": "8AM-4PM"
      },
      "reviews_per_score": {
        "1": 1,
        "2": 0,
        "3": 0,
        "4": 0,
        "5": 4
      },
      "business_status": "OPERATIONAL",
      "is_verified": false,
      "is_claimed": false
    },
    {
      "slug": "stephens-and-soetenga",
      "name": "Stephens & Soetenga",
      "category": "Accountant",
      "phone": "+1 317-841-1900",
      "site": "https://fisherscpa.com/",
      "address": "9845 E 116th St #100, Fishers, IN 46037",
      "latitude": 39.956220599999995,
      "longitude": -85.99341849999999,
      "rating": 5,
      "reviews": 2,
      "logo": "https://lh3.googleusercontent.com/-upfHamI-3Yw/AAAAAAAAAAI/AAAAAAAAAAA/Ma8umS1p5Ew/s44-p-k-no-ns-nd/photo.jpg",
      "photo": "https://streetviewpixels-pa.googleapis.com/v1/thumbnail?panoid=aLkskm2ABJJnjGJ-uk6NcQ&cb_client=search.gws-prod.gps&w=800&h=500&yaw=194.29703&pitch=0&thumbfov=100",
      "working_hours": {
        "Friday": "Closed",
        "Monday": "9AM-1PM",
        "Saturday": "Closed",
        "Sunday": "Closed",
        "Thursday": "9AM-1PM",
        "Tuesday": "9AM-1PM",
        "Wednesday": "9AM-1PM"
      },
      "reviews_per_score": {
        "1": 0,
        "2": 0,
        "3": 0,
        "4": 0,
        "5": 2
      },
      "business_status": "OPERATIONAL",
      "is_verified": true,
      "is_claimed": true
    },
    {
      "slug": "amr-tax-and-accounting-services",
      "name": "Amr Tax & Accounting Services",
      "category": "Accounting firm",
      "phone": "+1 732-500-5941",
      "site": "https://www.amrtax.net/",
      "address": "14074 Trade Center Dr Suite 124, Fishers, IN 46038",
      "latitude": 39.991004499999995,
      "longitude": -86.0060831,
      "rating": 5,
      "reviews": 51,
      "logo": "https://lh4.googleusercontent.com/-lCcgzV6xQbk/AAAAAAAAAAI/AAAAAAAAAAA/drAB7EWCNz4/s44-p-k-no-ns-nd/photo.jpg",
      "photo": "https://lh3.googleusercontent.com/gps-cs-s/APNQkAG4Jd_fZGYdVHetp5HdQA2MuwRF91i8b0YGVkC41AOuZ8rtI2gz0xvAbsvn_u_zSmYyg4tXuTbsdAza9nFo22nM2AJ9ePsgoRQzisvRMOXVujAzsDSjjIs4sKpVcuNPD-I8TPI=w800-h500-k-no",
      "working_hours": {
        "Friday": "6-10PM",
        "Monday": "6-10PM",
        "Saturday": "9AM-1PM",
        "Sunday": "9AM-1PM",
        "Thursday": "6-10PM",
        "Tuesday": "6-10PM",
        "Wednesday": "6-10PM"
      },
      "reviews_per_score": {
        "1": 0,
        "2": 0,
        "3": 0,
        "4": 0,
        "5": 51
      },
      "business_status": "OPERATIONAL",
      "is_verified": true,
      "is_claimed": true
    },
    {
      "slug": "lionheart-tax-and-accounting-llc",
      "name": "Lionheart Tax and Accounting, LLC",
      "category": "Tax preparation service",
      "phone": "+1 317-597-0606",
      "site": "http://www.lionhearttaxandaccounting.com/",
      "address": "10142 Brooks School Rd UNIT 206, Fishers, IN 46037",
      "latitude": 39.9355149,
      "longitude": -85.9485651,
      "rating": 3.5,
      "reviews": 11,
      "logo": "",
      "photo": "",
      "working_hours": {
        "Monday": "Closed",
        "Tuesday": "Closed",
        "Wednesday": "Closed",
        "Thursday": "Closed",
        "Friday": "Closed",
        "Saturday": "Closed",
        "Sunday": "Closed"
      },
      "reviews_per_score": {
        "1": 4,
        "2": 0,
        "3": 0,
        "4": 0,
        "5": 7
      },
      "business_status": "OPERATIONAL",
      "is_verified": false,
      "is_claimed": false
    },
    {
      "slug": "cook-graber-and-company-llc",
      "name": "Cook, Graber & Company, LLC",
      "category": "Certified public accountant",
      "phone": "+1 317-577-4150",
      "site": "http://www.cookgraber.com/",
      "address": "12953 Publishers Dr Ste 200, Fishers, IN 46038",
      "latitude": 39.9761449,
      "longitude": -86.00178489999999,
      "rating": 5,
      "reviews": 2,
      "logo": "https://lh3.googleusercontent.com/-Yor2Wgioo7Y/AAAAAAAAAAI/AAAAAAAAAAA/lgDZVX9Towc/s44-p-k-no-ns-nd/photo.jpg",
      "photo": "https://streetviewpixels-pa.googleapis.com/v1/thumbnail?panoid=1w8jgF_gSKjr9FCFy7pHAw&cb_client=search.gws-prod.gps&w=800&h=500&yaw=154.03735&pitch=0&thumbfov=100",
      "working_hours": {
        "Friday": "8AM-5PM",
        "Monday": "8AM-5PM",
        "Saturday": "Closed",
        "Sunday": "Closed",
        "Thursday": "8AM-5PM",
        "Tuesday": "8AM-5PM",
        "Wednesday": "8AM-5PM"
      },
      "reviews_per_score": {
        "1": 0,
        "2": 0,
        "3": 0,
        "4": 0,
        "5": 2
      },
      "business_status": "OPERATIONAL",
      "is_verified": true,
      "is_claimed": true
    },
    {
      "slug": "erwin-cpa-group",
      "name": "Erwin CPA Group",
      "category": "Accountant",
      "phone": "+1 317-408-5592",
      "site": "http://www.erwincpagroup.com/",
      "address": "14074 Trade Center Dr, Fishers, IN 46038",
      "latitude": 39.9910083,
      "longitude": -86.0060791,
      "rating": 5,
      "reviews": 2,
      "logo": "https://lh4.googleusercontent.com/-vmmZ2sPGYu0/AAAAAAAAAAI/AAAAAAAAAAA/4XTSWRim02U/s44-p-k-no-ns-nd/photo.jpg",
      "photo": "https://streetviewpixels-pa.googleapis.com/v1/thumbnail?panoid=K55P0Rf0_i2c7nWty5Zv_w&cb_client=search.gws-prod.gps&w=800&h=500&yaw=181.90387&pitch=0&thumbfov=100",
      "working_hours": {
        "Friday": "8:30AM-5PM",
        "Monday": "8:30AM-5PM",
        "Saturday": "Closed",
        "Sunday": "Closed",
        "Thursday": "8:30AM-5PM",
        "Tuesday": "8:30AM-5PM",
        "Wednesday": "8:30AM-5PM"
      },
      "reviews_per_score": {
        "1": 0,
        "2": 0,
        "3": 0,
        "4": 0,
        "5": 2
      },
      "business_status": "OPERATIONAL",
      "is_verified": true,
      "is_claimed": true
    },
    {
      "slug": "indy-tax-queens-llc",
      "name": "Indy Tax Queens LLC",
      "category": "Accountant",
      "phone": "+1 317-832-2317",
      "site": "http://www.indytaxqueens.com/",
      "address": "11 Municipal Dr UNIT 200, Fishers, IN 46038",
      "latitude": 39.9608683,
      "longitude": -86.0166575,
      "rating": 4.8,
      "reviews": 49,
      "logo": "https://lh4.googleusercontent.com/-j1XIIzcxeZw/AAAAAAAAAAI/AAAAAAAAAAA/Of9V8gjqQf0/s44-p-k-no-ns-nd/photo.jpg",
      "photo": "https://streetviewpixels-pa.googleapis.com/v1/thumbnail?panoid=JTTN7DVuD_ilB-ZLTiizuQ&cb_client=search.gws-prod.gps&w=800&h=500&yaw=26.019224&pitch=0&thumbfov=100",
      "working_hours": {
        "Monday": "Closed",
        "Tuesday": "Closed",
        "Wednesday": "Closed",
        "Thursday": "Closed",
        "Friday": "Closed",
        "Saturday": "Closed",
        "Sunday": "Closed"
      },
      "reviews_per_score": {
        "1": 2,
        "2": 0,
        "3": 0,
        "4": 0,
        "5": 47
      },
      "business_status": "OPERATIONAL",
      "is_verified": true,
      "is_claimed": true
    },
    {
      "slug": "mckee-and-gunderson-pc",
      "name": "McKee & Gunderson PC",
      "category": "Certified public accountant",
      "phone": "+1 317-288-5266",
      "site": "http://www.indycpas.com/",
      "address": "10412 Allisonville Rd Unit 210, Fishers, IN 46038",
      "latitude": 39.939675099999995,
      "longitude": -86.052712,
      "rating": 5,
      "reviews": 1,
      "logo": "https://lh6.googleusercontent.com/-TnXNI_-dD1A/AAAAAAAAAAI/AAAAAAAAAAA/4FNrpqzzkVY/s44-p-k-no-ns-nd/photo.jpg",
      "photo": "",
      "working_hours": {
        "Friday": "8AM-5PM",
        "Monday": "8AM-5PM",
        "Saturday": "Closed",
        "Sunday": "Closed",
        "Thursday": "8AM-5PM",
        "Tuesday": "8AM-5PM",
        "Wednesday": "8AM-5PM"
      },
      "reviews_per_score": {
        "1": 0,
        "2": 0,
        "3": 0,
        "4": 0,
        "5": 1
      },
      "business_status": "OPERATIONAL",
      "is_verified": true,
      "is_claimed": true
    },
    {
      "slug": "rich-driscol-cpa",
      "name": "Rich Driscol CPA",
      "category": "Accountant",
      "phone": "+1 317-413-8338",
      "site": "https://richdriscolcpa.com/",
      "address": "10350 Cressida Way, Fishers, IN 46037",
      "latitude": 39.9391193,
      "longitude": -85.947599,
      "rating": 5,
      "reviews": 1,
      "logo": "https://lh6.googleusercontent.com/-AJrh0uidjyY/AAAAAAAAAAI/AAAAAAAAAAA/NnQLG3QkyIM/s44-p-k-no-ns-nd/photo.jpg",
      "photo": "https://streetviewpixels-pa.googleapis.com/v1/thumbnail?panoid=mZ0Psp51qP_NucVbhczftQ&cb_client=search.gws-prod.gps&w=800&h=500&yaw=291.43463&pitch=0&thumbfov=100",
      "working_hours": {
        "Friday": "9AM-5PM",
        "Monday": "9AM-5PM",
        "Saturday": "Closed",
        "Sunday": "Closed",
        "Thursday": "9AM-5PM",
        "Tuesday": "9AM-5PM",
        "Wednesday": "9AM-5PM"
      },
      "reviews_per_score": {
        "1": 0,
        "2": 0,
        "3": 0,
        "4": 0,
        "5": 1
      },
      "business_status": "OPERATIONAL",
      "is_verified": true,
      "is_claimed": true
    },
    {
      "slug": "chamberlain-accounting-solutions",
      "name": "Chamberlain Accounting Solutions",
      "category": "Bookkeeping service",
      "phone": "+1 317-558-9607",
      "site": "http://www.chamberlainaccountingsolutions.com/",
      "address": "11842 Castlestone Dr, Fishers, IN 46037",
      "latitude": 39.9654069,
      "longitude": -85.95452399999999,
      "rating": 5,
      "reviews": 11,
      "logo": "https://lh3.googleusercontent.com/-WBafIGf4oB0/AAAAAAAAAAI/AAAAAAAAAAA/OfeTVvm4cuw/s44-p-k-no-ns-nd/photo.jpg",
      "photo": "https://streetviewpixels-pa.googleapis.com/v1/thumbnail?panoid=YNoHP0sOa0g6IE_hhsCRJA&cb_client=search.gws-prod.gps&w=800&h=500&yaw=354.9523&pitch=0&thumbfov=100",
      "working_hours": {
        "Friday": "8AM-5PM",
        "Monday": "8AM-5PM",
        "Saturday": "Closed",
        "Sunday": "Closed",
        "Thursday": "8AM-5PM",
        "Tuesday": "8AM-5PM",
        "Wednesday": "8AM-5PM"
      },
      "reviews_per_score": {
        "1": 0,
        "2": 0,
        "3": 0,
        "4": 0,
        "5": 11
      },
      "business_status": "OPERATIONAL",
      "is_verified": true,
      "is_claimed": true
    },
    {
      "slug": "haines-renita-cpa",
      "name": "Haines Renita CPA",
      "category": "Accountant",
      "phone": "+1 317-849-6385",
      "site": "",
      "address": "7735 Loma Ct, Fishers, IN 46038",
      "latitude": 39.939747,
      "longitude": -86.0287925,
      "rating": 5,
      "reviews": 1,
      "logo": "",
      "photo": "https://streetviewpixels-pa.googleapis.com/v1/thumbnail?panoid=1xG3iNl76k_6neFktQiE9g&cb_client=search.gws-prod.gps&w=800&h=500&yaw=61.385582&pitch=0&thumbfov=100",
      "working_hours": {
        "Friday": "8AM-5PM",
        "Monday": "8AM-5PM",
        "Saturday": "Closed",
        "Sunday": "Closed",
        "Thursday": "8AM-5PM",
        "Tuesday": "8AM-5PM",
        "Wednesday": "8AM-5PM"
      },
      "reviews_per_score": {
        "1": 0,
        "2": 0,
        "3": 0,
        "4": 0,
        "5": 1
      },
      "business_status": "OPERATIONAL",
      "is_verified": false,
      "is_claimed": false
    },
    {
      "slug": "whitinger-and-company-llc",
      "name": "Whitinger & Company LLC",
      "category": "Certified public accountant",
      "phone": "+1 317-841-6009",
      "site": "http://www.whitinger.com/",
      "address": "10735 Sky Prairie St STE 100, Fishers, IN 46038",
      "latitude": 39.9440975,
      "longitude": -86.0192704,
      "rating": 4,
      "reviews": 6,
      "logo": "https://lh6.googleusercontent.com/-9XzjJTGPLxw/AAAAAAAAAAI/AAAAAAAAAAA/3Mohsu6yj4g/s44-p-k-no-ns-nd/photo.jpg",
      "photo": "https://lh3.googleusercontent.com/gps-cs-s/APNQkAFVDzTRf4pQdsfvXkZm-Nz9BSFcJO3GvTmohDm2pS4j_BniN5aphBJJKezmtZ5fOBmZk_KY0psErZtkzM5lmk156mMO-4jYZRvFL7UORygQQfeVjrXAv6FK-3CWNvuK26UEGlTbSQ=w800-h500-k-no",
      "working_hours": {
        "Friday": "8AM-5PM",
        "Monday": "8AM-5PM",
        "Saturday": "Closed",
        "Sunday": "Closed",
        "Thursday": "8AM-5PM",
        "Tuesday": "8AM-5PM",
        "Wednesday": "8AM-5PM"
      },
      "reviews_per_score": {
        "1": 0,
        "2": 2,
        "3": 0,
        "4": 0,
        "5": 4
      },
      "business_status": "OPERATIONAL",
      "is_verified": true,
      "is_claimed": true
    },
    {
      "slug": "rektio-accounting",
      "name": "Rektio Accounting",
      "category": "Certified public accountant",
      "phone": "+1 317-954-5067",
      "site": "http://www.rektio.com/",
      "address": "12175 Visionary Way #760, Fishers, IN 46038",
      "latitude": 39.966761999999996,
      "longitude": -86.008639,
      "rating": 5,
      "reviews": 4,
      "logo": "https://lh3.googleusercontent.com/-nsr03TB9AUY/AAAAAAAAAAI/AAAAAAAAAAA/Gu3U0xyO40k/s44-p-k-no-ns-nd/photo.jpg",
      "photo": "https://streetviewpixels-pa.googleapis.com/v1/thumbnail?panoid=HkFpnH864HkHGIdRq12bbA&cb_client=search.gws-prod.gps&w=800&h=500&yaw=298.3952&pitch=0&thumbfov=100",
      "working_hours": {
        "Friday": "8AM-4PM",
        "Monday": "8AM-4PM",
        "Saturday": "Closed",
        "Sunday": "Closed",
        "Thursday": "8AM-4PM",
        "Tuesday": "8AM-4PM",
        "Wednesday": "8AM-4PM"
      },
      "reviews_per_score": {
        "1": 0,
        "2": 0,
        "3": 0,
        "4": 0,
        "5": 4
      },
      "business_status": "OPERATIONAL",
      "is_verified": true,
      "is_claimed": true
    }
  ]
}