{
  "city": "Franklin",
  "state": "Tennessee",
  "state_code": "TN",
  "city_slug": "franklin",
  "state_slug": "tennessee",
  "firm_count": 20,
  "firms": [
    {
      "slug": "white-olive-cpa-llc",
      "name": "White Olive CPA, LLC",
      "category": "Certified public accountant",
      "phone": "+1 833-820-2255",
      "site": "https://www.whiteolivecpa.com/%3Futm_source%3DGBP%26utm_medium%3Dorganic%26utm_campaign%3Dfranklin",
      "address": "109 Holiday Ct STE D9, Franklin, TN 37067",
      "latitude": 35.9165981,
      "longitude": -86.82655919999999,
      "rating": 4.8,
      "reviews": 46,
      "logo": "https://lh6.googleusercontent.com/-uRNdmsZkCGc/AAAAAAAAAAI/AAAAAAAAAAA/eA0c_fd4NFA/s44-p-k-no-ns-nd/photo.jpg",
      "photo": "https://lh3.googleusercontent.com/gps-cs-s/APNQkAGBLa0L1CFNjTwNzboNjozRSf_J49aMDSGPzKU9pxdntQUAGaM-eAU5ywbt51W0sQNJk3B_tKW8rm4tYDU5bMTKGdgLyP4a8CkmGufvlIbarZJsdFLRFsk2UFqDeCLaaJ0amM1Dlg=w800-h500-k-no",
      "working_hours": {
        "Friday": "9AM-5PM",
        "Monday": "9AM-5PM",
        "Saturday": "Closed",
        "Sunday": "Closed",
        "Thursday": "9AM-5PM",
        "Tuesday": "9AM-5PM",
        "Wednesday": "9AM-5PM"
      },
      "reviews_per_score": {
        "1": 2,
        "2": 0,
        "3": 0,
        "4": 0,
        "5": 44
      },
      "business_status": "OPERATIONAL",
      "is_verified": true,
      "is_claimed": true
    },
    {
      "slug": "cummings-cpa-services",
      "name": "Cummings CPA Services",
      "category": "Tax preparation service",
      "phone": "+1 615-807-1918",
      "site": "http://www.cummingscpaservices.com/",
      "address": "2550 Meridian Blvd, Franklin, TN 37067",
      "latitude": 35.9516486,
      "longitude": -86.8091082,
      "rating": 4.8,
      "reviews": 16,
      "logo": "https://lh3.googleusercontent.com/-PAMW9PDLdis/AAAAAAAAAAI/AAAAAAAAAAA/LMOdnm3mg1M/s44-p-k-no-ns-nd/photo.jpg",
      "photo": "https://streetviewpixels-pa.googleapis.com/v1/thumbnail?panoid=HNDR8ytIJ9pJK3jwnUn3zg&cb_client=search.gws-prod.gps&w=800&h=500&yaw=172.51923&pitch=0&thumbfov=100",
      "working_hours": {
        "Friday": "8AM-5PM",
        "Monday": "8AM-5PM",
        "Saturday": "Closed",
        "Sunday": "Closed",
        "Thursday": "8AM-5PM",
        "Tuesday": "8AM-5PM",
        "Wednesday": "8AM-5PM"
      },
      "reviews_per_score": {
        "1": 1,
        "2": 0,
        "3": 0,
        "4": 0,
        "5": 15
      },
      "business_status": "OPERATIONAL",
      "is_verified": true,
      "is_claimed": true
    },
    {
      "slug": "shelby-cpas-pllc",
      "name": "Shelby CPAs, PLLC",
      "category": "Certified public accountant",
      "phone": "+1 615-473-0013",
      "site": "https://www.linkedin.com/in/lanceshelbycpa/",
      "address": "249 4th Ave N, Franklin, TN 37064",
      "latitude": 35.9271995,
      "longitude": -86.8725484,
      "rating": 5,
      "reviews": 43,
      "logo": "https://lh6.googleusercontent.com/-u7CgduVVZFE/AAAAAAAAAAI/AAAAAAAAAAA/2PxUMMjj3XA/s44-p-k-no-ns-nd/photo.jpg",
      "photo": "https://streetviewpixels-pa.googleapis.com/v1/thumbnail?panoid=7jF0cwBMpcb7INgMAjzOtw&cb_client=search.gws-prod.gps&w=800&h=500&yaw=236.45328&pitch=0&thumbfov=100",
      "working_hours": {
        "Friday": "9AM-5PM",
        "Monday": "9AM-5PM",
        "Saturday": "Closed",
        "Sunday": "Closed",
        "Thursday": "9AM-5PM",
        "Tuesday": "9AM-5PM",
        "Wednesday": "9AM-5PM"
      },
      "reviews_per_score": {
        "1": 0,
        "2": 0,
        "3": 0,
        "4": 0,
        "5": 43
      },
      "business_status": "OPERATIONAL",
      "is_verified": true,
      "is_claimed": true
    },
    {
      "slug": "smith-wynd-cpa",
      "name": "Smith Wynd CPA",
      "category": "Accountant",
      "phone": "+1 615-794-8881",
      "site": "https://smithwynd.com/",
      "address": "9000 Carothers Pkwy #100, Franklin, TN 37067",
      "latitude": 35.955698999999996,
      "longitude": -86.8031809,
      "rating": 4,
      "reviews": 18,
      "logo": "",
      "photo": "https://streetviewpixels-pa.googleapis.com/v1/thumbnail?panoid=hteVN5aNFymp---ALuVmkw&cb_client=search.gws-prod.gps&w=800&h=500&yaw=108.369316&pitch=0&thumbfov=100",
      "working_hours": {
        "Friday": "8:30AM-5PM",
        "Monday": "8:30AM-5PM",
        "Saturday": "Closed",
        "Sunday": "Closed",
        "Thursday": "8:30AM-5PM",
        "Tuesday": "8:30AM-5PM",
        "Wednesday": "8:30AM-5PM"
      },
      "reviews_per_score": {
        "1": 4,
        "2": 0,
        "3": 1,
        "4": 0,
        "5": 13
      },
      "business_status": "OPERATIONAL",
      "is_verified": false,
      "is_claimed": false
    },
    {
      "slug": "sims-cpa-consulting-pllc",
      "name": "Sims CPA Consulting PLLC",
      "category": "Certified public accountant",
      "phone": "+1 615-435-9131",
      "site": "http://www.simscpa.com/",
      "address": "1881 General George Patton Dr #104, Franklin, TN 37067",
      "latitude": 35.958196,
      "longitude": -86.832246,
      "rating": 4.6,
      "reviews": 11,
      "logo": "https://lh4.googleusercontent.com/-kF6fJYwmD-o/AAAAAAAAAAI/AAAAAAAAAAA/PsOcPwAjU_g/s44-p-k-no-ns-nd/photo.jpg",
      "photo": "https://lh3.googleusercontent.com/gps-cs-s/APNQkAFTeW6V1Z1xr0w2huw3UoutCOyEtSeuy9sXlPmn5H_UeaX5jdYekrilpAdfJT34rU21k0PTH1owyrstMQg4CIXI8XNX1u3dUVzVjLhP8LrGS9Uc2tVlv0xWUpHmX_AmKsYGgaXk=w800-h500-k-no",
      "working_hours": {
        "Friday": "8:30AM-5PM",
        "Monday": "8:30AM-5PM",
        "Saturday": "Closed",
        "Sunday": "Closed",
        "Thursday": "8:30AM-5PM",
        "Tuesday": "8:30AM-5PM",
        "Wednesday": "8:30AM-5PM"
      },
      "reviews_per_score": {
        "1": 1,
        "2": 0,
        "3": 0,
        "4": 0,
        "5": 10
      },
      "business_status": "OPERATIONAL",
      "is_verified": true,
      "is_claimed": true
    },
    {
      "slug": "jason-moll-cpa",
      "name": "Jason Moll, CPA",
      "category": "Tax consultant",
      "phone": "+1 615-600-0122",
      "site": "http://jasonmollcpa.com/",
      "address": "1030 16th Ave S STE 200, Nashville, TN 37212",
      "latitude": 36.1445653,
      "longitude": -86.7925834,
      "rating": 4.8,
      "reviews": 13,
      "logo": "https://lh4.googleusercontent.com/-ismJNDIdv2s/AAAAAAAAAAI/AAAAAAAAAAA/9k2Ccg6aljQ/s44-p-k-no-ns-nd/photo.jpg",
      "photo": "https://lh3.googleusercontent.com/gps-cs-s/APNQkAGFDwtN4lM1IBh-Y_qd2wIS15SzfvbqMb70xFm0QW9_s85epsORjfxg6fRx21bOoFs_F9o0jk7R_QogJVnU5cG5Zs-kayonIen3c9RvJw2E113FmhQQdgoBD2awUacXzaB_3dftPA9OXf0=w800-h500-k-no",
      "working_hours": {
        "Friday": "9AM-5PM",
        "Monday": "9AM-5PM",
        "Saturday": "Closed",
        "Sunday": "Closed",
        "Thursday": "9AM-5PM",
        "Tuesday": "9AM-5PM",
        "Wednesday": "9AM-5PM"
      },
      "reviews_per_score": {
        "1": 0,
        "2": 1,
        "3": 0,
        "4": 0,
        "5": 12
      },
      "business_status": "OPERATIONAL",
      "is_verified": true,
      "is_claimed": true
    },
    {
      "slug": "frazier-and-associates-cpas",
      "name": "Frazier & Associates CPA's",
      "category": "Tax preparation service",
      "phone": "+1 615-794-1375",
      "site": "http://www.frazier-cpas.com/",
      "address": "284 Seaboard Ln Suite 110, Franklin, TN 37067",
      "latitude": 35.950958799999995,
      "longitude": -86.8282311,
      "rating": 3.7,
      "reviews": 6,
      "logo": "https://lh4.googleusercontent.com/-rzgW6OgHv98/AAAAAAAAAAI/AAAAAAAAAAA/qUm-zV3bL4A/s44-p-k-no-ns-nd/photo.jpg",
      "photo": "https://lh3.googleusercontent.com/gps-cs-s/APNQkAEUL7YPcRCzL1iXvOu7VO1-FbWRUHT0FnxUhsEx5DU7h1iN_r8c5T9zuRE5zFcM7v9iIn3fHcS2-O3PWBl02RznOvKylQbSP_v5s1xvzr6oIAc37QyL4ZfE-wfJz0Z1J6icJCQF=w800-h500-k-no",
      "working_hours": {
        "Friday": "8AM-5PM",
        "Monday": "8AM-5PM",
        "Saturday": "Closed",
        "Sunday": "Closed",
        "Thursday": "8AM-5PM",
        "Tuesday": "8AM-5PM",
        "Wednesday": "8AM-5PM"
      },
      "reviews_per_score": {
        "1": 2,
        "2": 0,
        "3": 0,
        "4": 0,
        "5": 4
      },
      "business_status": "OPERATIONAL",
      "is_verified": true,
      "is_claimed": true
    },
    {
      "slug": "uhy",
      "name": "UHY",
      "category": "Accounting firm",
      "phone": "+1 615-750-5537",
      "site": "https://uhy-us.com/locations/tennessee/nashville-tn-cpa%3Futm_source%3Dgoogle%26utm_medium%3Dorganic%26utm_campaign%3Dgmb",
      "address": "3000 Meridian Blvd STE 300, Franklin, TN 37067",
      "latitude": 35.9526676,
      "longitude": -86.8100688,
      "rating": 4.4,
      "reviews": 33,
      "logo": "https://lh3.googleusercontent.com/-YsnKOlbAw78/AAAAAAAAAAI/AAAAAAAAAAA/iNYskvUIIoc/s44-p-k-no-ns-nd/photo.jpg",
      "photo": "https://lh3.googleusercontent.com/gps-cs-s/APNQkAGaj3Lhhcfl1mVK1C8v0g_73zFxpNvEdoV4oXTELtaON9ClPcxgDnLno34P0q-gJrusgzLrvEA5HvjgqOHTANxFz-82OOSby6Hnc1-rDHsNO0eZVZ39LlNuw77lN95Xvf62aopT=w800-h500-k-no",
      "working_hours": {
        "Friday": "8AM-5PM",
        "Monday": "8AM-5PM",
        "Saturday": "Closed",
        "Sunday": "Closed",
        "Thursday": "8AM-5PM",
        "Tuesday": "8AM-5PM",
        "Wednesday": "8AM-5PM"
      },
      "reviews_per_score": {
        "1": 5,
        "2": 0,
        "3": 0,
        "4": 0,
        "5": 28
      },
      "business_status": "OPERATIONAL",
      "is_verified": true,
      "is_claimed": true
    },
    {
      "slug": "lange-accounting-and-financial-services",
      "name": "Lange Accounting & Financial Services",
      "category": "Certified public accountant",
      "phone": "+1 615-716-9551",
      "site": "https://www.langeaccounting.com/",
      "address": "407 Church St # 2, Franklin, TN 37064",
      "latitude": 35.9224779,
      "longitude": -86.869789,
      "rating": 5,
      "reviews": 10,
      "logo": "https://lh4.googleusercontent.com/-1jDRyOWgzZs/AAAAAAAAAAI/AAAAAAAAAAA/0DZV64x1Fd8/s44-p-k-no-ns-nd/photo.jpg",
      "photo": "https://streetviewpixels-pa.googleapis.com/v1/thumbnail?panoid=JsgV1nWmwERzAr1MVv92fg&cb_client=search.gws-prod.gps&w=800&h=500&yaw=147.69167&pitch=0&thumbfov=100",
      "working_hours": {
        "Friday": "8AM-4PM",
        "Monday": "8AM-4PM",
        "Saturday": "Closed",
        "Sunday": "Closed",
        "Thursday": "8AM-4PM",
        "Tuesday": "8AM-4PM",
        "Wednesday": "8AM-4PM"
      },
      "reviews_per_score": {
        "1": 0,
        "2": 0,
        "3": 0,
        "4": 0,
        "5": 10
      },
      "business_status": "OPERATIONAL",
      "is_verified": true,
      "is_claimed": true
    },
    {
      "slug": "hildreth-and-associates-cpa",
      "name": "Hildreth & Associates CPA",
      "category": "Certified public accountant",
      "phone": "+1 408-371-0711",
      "site": "https://www.hildrethcpa.com/",
      "address": "9045 Carothers Pkwy #202, Franklin, TN 37067",
      "latitude": 35.957874,
      "longitude": -86.8032295,
      "rating": 5,
      "reviews": 1,
      "logo": "https://lh6.googleusercontent.com/-PW3sweDB_Wc/AAAAAAAAAAI/AAAAAAAAAAA/3E6VhlX4U30/s44-p-k-no-ns-nd/photo.jpg",
      "photo": "https://lh3.googleusercontent.com/gps-cs-s/APNQkAEhhuYDL5WUnPotc-PeoOZMWw8uNcQPJ42ORfuCsAY35BNclg-wjs-awUppBrrsSGpH0caJI5bk6TbDbmRnudu2u5WwgiAEQvUYTqoLtNODK_ymcXzsdJwYcOV2NlUkG_Jd_8gl=w800-h500-k-no",
      "working_hours": {
        "Friday": "9AM-5PM",
        "Monday": "9AM-5PM",
        "Saturday": "Closed",
        "Sunday": "Closed",
        "Thursday": "9AM-5PM",
        "Tuesday": "9AM-5PM",
        "Wednesday": "9AM-5PM"
      },
      "reviews_per_score": {
        "1": 0,
        "2": 0,
        "3": 0,
        "4": 0,
        "5": 1
      },
      "business_status": "OPERATIONAL",
      "is_verified": true,
      "is_claimed": true
    },
    {
      "slug": "tennessee-tax-solutions",
      "name": "Tennessee Tax Solutions",
      "category": "Accountant",
      "phone": "+1 615-224-3661",
      "site": "http://tenntaxes.com/%3Futm_source%3Dgoogle%26utm_medium%3Dwix_google_business_profile%26utm_campaign%3D3369118061297060281",
      "address": "106 Mission Ct Suite 604B, Franklin, TN 37067",
      "latitude": 35.938504099999996,
      "longitude": -86.8327357,
      "rating": 4.9,
      "reviews": 100,
      "logo": "https://lh6.googleusercontent.com/-E-XPQO1swGw/AAAAAAAAAAI/AAAAAAAAAAA/EPivR_Uoey0/s44-p-k-no-ns-nd/photo.jpg",
      "photo": "https://lh3.googleusercontent.com/gps-cs-s/APNQkAGWGOGaVQz-kdbRx_hN2xMzqUDRxp4tCJ2v_DjDYixV8Tc6mkcWFCTaqhX5Vcog-Lu6F3bq0ZGupc2uEcull-MUHtgXMtXhKqPRMqW1KmGr2zSOf9IJIaJ96R7BzbHgD_0SO0Cr=w800-h500-k-no",
      "working_hours": {
        "Monday": "Closed",
        "Tuesday": "Closed",
        "Wednesday": "Closed",
        "Thursday": "Closed",
        "Friday": "Closed",
        "Saturday": "Closed",
        "Sunday": "Closed"
      },
      "reviews_per_score": {
        "1": 2,
        "2": 0,
        "3": 0,
        "4": 0,
        "5": 98
      },
      "business_status": "OPERATIONAL",
      "is_verified": true,
      "is_claimed": true
    },
    {
      "slug": "moyer-and-co",
      "name": "Moyer & Co",
      "category": "Bookkeeping service",
      "phone": "+1 615-224-8400",
      "site": "http://www.moyerco.com/",
      "address": "202 3rd Ave N, Franklin, TN 37064",
      "latitude": 35.9269852,
      "longitude": -86.8699156,
      "rating": 5,
      "reviews": 3,
      "logo": "https://lh3.googleusercontent.com/-1b4mp1ztM-c/AAAAAAAAAAI/AAAAAAAAAAA/23jTMFevi7c/s44-p-k-no-ns-nd/photo.jpg",
      "photo": "https://streetviewpixels-pa.googleapis.com/v1/thumbnail?panoid=sCSUKRufLftWqLS3SlTzkQ&cb_client=search.gws-prod.gps&w=800&h=500&yaw=53.07627&pitch=0&thumbfov=100",
      "working_hours": {
        "Friday": "8AM-4PM",
        "Monday": "8AM-4PM",
        "Saturday": "Closed",
        "Sunday": "Closed",
        "Thursday": "8AM-4PM",
        "Tuesday": "8AM-4PM",
        "Wednesday": "8AM-4PM"
      },
      "reviews_per_score": {
        "1": 0,
        "2": 0,
        "3": 0,
        "4": 0,
        "5": 3
      },
      "business_status": "OPERATIONAL",
      "is_verified": true,
      "is_claimed": true
    },
    {
      "slug": "spain-and-higginbotham-cpa-group-pllc",
      "name": "Spain & Higginbotham CPA Group, PLLC",
      "category": "Tax preparation service",
      "phone": "+1 615-794-8100",
      "site": "https://www.franklincpas.com/",
      "address": "1127 W Main St, Franklin, TN 37064",
      "latitude": 35.9196929,
      "longitude": -86.87957,
      "rating": 5,
      "reviews": 1,
      "logo": "https://lh6.googleusercontent.com/-jeQ__9Wx_Ao/AAAAAAAAAAI/AAAAAAAAAAA/39xQXHsda2c/s44-p-k-no-ns-nd/photo.jpg",
      "photo": "https://lh3.googleusercontent.com/gps-cs-s/APNQkAE2qgK12KUwf9CX-pH79DR5RWaiqPKoc8DWWH0bHvPUgVRw3T1VYUP4IP2Iiyy244Z-BZQQTUsBfGOaKaU-rn711wUqUAD5uAchhNWz6x9RNjnGW4esqyxAqiQCdOkwn30l8_8=w800-h500-k-no",
      "working_hours": {
        "Friday": "8AM-5PM",
        "Monday": "8AM-5PM",
        "Saturday": "Closed",
        "Sunday": "Closed",
        "Thursday": "8AM-5PM",
        "Tuesday": "8AM-5PM",
        "Wednesday": "8AM-5PM"
      },
      "reviews_per_score": {
        "1": 0,
        "2": 0,
        "3": 0,
        "4": 0,
        "5": 1
      },
      "business_status": "OPERATIONAL",
      "is_verified": true,
      "is_claimed": true
    },
    {
      "slug": "humphres-and-associates-pc",
      "name": "Humphres & Associates PC",
      "category": "Accountant",
      "phone": "+1 615-256-1111",
      "site": "http://www.humphrescpa.com/",
      "address": "342 Cool Springs Blvd #101, Franklin, TN 37067",
      "latitude": 35.942864199999995,
      "longitude": -86.82887439999999,
      "rating": 3.7,
      "reviews": 18,
      "logo": "https://lh5.googleusercontent.com/-0NKp51t3vzQ/AAAAAAAAAAI/AAAAAAAAAAA/vUhT4soceXE/s44-p-k-no-ns-nd/photo.jpg",
      "photo": "https://lh3.googleusercontent.com/gps-cs-s/APNQkAGu0mQugN1WZgFDCL48Ao3_GcW-oNl6Dl_etDl2FWx4IyL8CFCxKsWBvPqvvFLmnp8kUIctBCkGWg5G0tRpPnz4Kp7H_TjiiaAh33t5SCpZ4csKPrA3aqcfkEoIxENZlJRw8OADWQ=w800-h500-k-no",
      "working_hours": {
        "Friday": "8AM-5PM",
        "Monday": "8AM-5PM",
        "Saturday": "Closed",
        "Sunday": "Closed",
        "Thursday": "8AM-5PM",
        "Tuesday": "8AM-5PM",
        "Wednesday": "8AM-5PM"
      },
      "reviews_per_score": {
        "1": 6,
        "2": 0,
        "3": 0,
        "4": 0,
        "5": 12
      },
      "business_status": "OPERATIONAL",
      "is_verified": true,
      "is_claimed": true
    },
    {
      "slug": "riverridge-cpa-and-business-solutions-llc",
      "name": "RiverRidge CPA and Business Solutions LLC",
      "category": "Accounting firm",
      "phone": "+1 615-549-6536",
      "site": "http://www.riverridgecpa.com/",
      "address": "236 Public Square Suite 202, Franklin, TN 37064",
      "latitude": 35.9256996,
      "longitude": -86.8690057,
      "rating": 5,
      "reviews": 1,
      "logo": "https://lh5.googleusercontent.com/-XMZ5HqT1Ne8/AAAAAAAAAAI/AAAAAAAAAAA/YoKlLAQXHoE/s44-p-k-no-ns-nd/photo.jpg",
      "photo": "https://streetviewpixels-pa.googleapis.com/v1/thumbnail?panoid=uSyPNk2C_IZOHR_keqX3Vg&cb_client=search.gws-prod.gps&w=800&h=500&yaw=158.01375&pitch=0&thumbfov=100",
      "working_hours": {
        "Friday": "9AM-4PM",
        "Monday": "9AM-4PM",
        "Saturday": "Closed",
        "Sunday": "Closed",
        "Thursday": "9AM-4PM",
        "Tuesday": "9AM-4PM",
        "Wednesday": "9AM-4PM"
      },
      "reviews_per_score": {
        "1": 0,
        "2": 0,
        "3": 0,
        "4": 0,
        "5": 1
      },
      "business_status": "OPERATIONAL",
      "is_verified": true,
      "is_claimed": true
    },
    {
      "slug": "harmony-tax-services-cpa-pc",
      "name": "Harmony Tax Services CPA, PC",
      "category": "Certified public accountant",
      "phone": "+1 615-914-7215",
      "site": "https://harmonytaxcpa.com/",
      "address": "5105 Bond Ml Rd, Thompson's Station, TN 37179",
      "latitude": 35.787381599999996,
      "longitude": -86.8282151,
      "rating": 5,
      "reviews": 12,
      "logo": "https://lh3.googleusercontent.com/-vfSUczmbKhM/AAAAAAAAAAI/AAAAAAAAAAA/EicD5zoXs08/s44-p-k-no-ns-nd/photo.jpg",
      "photo": "https://lh3.googleusercontent.com/gps-cs-s/APNQkAF3EUfUc9jvb8PVz-vbev7oNzySXqaiEYg3YvUXdmCElmBU03gJcjBfJ1UmavZKFYqspJ55C-fP5tg62RC67iGRPVfxxwiudS8JGHIiId9Hv3_QasRqM0iLoE8Feqq6jqc9QDjGZ3Z4i_8s=w800-h500-k-no",
      "working_hours": {
        "Friday": "9AM-5PM",
        "Monday": "9AM-5PM",
        "Saturday": "Closed",
        "Sunday": "Closed",
        "Thursday": "9AM-5PM",
        "Tuesday": "9AM-5PM",
        "Wednesday": "9AM-5PM"
      },
      "reviews_per_score": {
        "1": 0,
        "2": 0,
        "3": 0,
        "4": 0,
        "5": 12
      },
      "business_status": "OPERATIONAL",
      "is_verified": true,
      "is_claimed": true
    },
    {
      "slug": "blankenship-cpa-group-pllc",
      "name": "Blankenship CPA Group, PLLC",
      "category": "Certified public accountant",
      "phone": "+1 615-373-3771",
      "site": "https://www.bcpas.com/",
      "address": "101 Winners Cir N, Brentwood, TN 37027",
      "latitude": 36.0381296,
      "longitude": -86.80808669999999,
      "rating": 4.3,
      "reviews": 39,
      "logo": "https://lh6.googleusercontent.com/-qqwlVAHPKXw/AAAAAAAAAAI/AAAAAAAAAAA/P1dBRXX3AD0/s44-p-k-no-ns-nd/photo.jpg",
      "photo": "https://lh3.googleusercontent.com/gps-cs-s/APNQkAHjjrgxvX496m4-37GM8BYvMg5ACAi4SdWmoHyauEQ-4y9xz2r5XTvCrHzg6MKh-NOIdHYTPV1-eNWYaAEP-jIdSIKMi4rLSguooSDem8RwphugQ8_bXJiPDqTmuSlaDpdilho=w800-h500-k-no",
      "working_hours": {
        "Friday": "8AM-5PM",
        "Monday": "8AM-5PM",
        "Saturday": "Closed",
        "Sunday": "Closed",
        "Thursday": "8AM-5PM",
        "Tuesday": "8AM-5PM",
        "Wednesday": "8AM-5PM"
      },
      "reviews_per_score": {
        "1": 6,
        "2": 1,
        "3": 0,
        "4": 2,
        "5": 30
      },
      "business_status": "OPERATIONAL",
      "is_verified": true,
      "is_claimed": true
    },
    {
      "slug": "miles-atnip-pllc",
      "name": "Miles Atnip, PLLC",
      "category": "Accountant",
      "phone": "+1 615-807-7870",
      "site": "https://milesatnip.com/",
      "address": "3325 Aspen Grove Dr STE 201, Franklin, TN 37067",
      "latitude": 35.9433948,
      "longitude": -86.8274572,
      "rating": 5,
      "reviews": 11,
      "logo": "https://lh4.googleusercontent.com/-AomI3y11KvQ/AAAAAAAAAAI/AAAAAAAAAAA/T2YDU1HSGZY/s44-p-k-no-ns-nd/photo.jpg",
      "photo": "https://streetviewpixels-pa.googleapis.com/v1/thumbnail?panoid=8eszjUBO231vFXZmFKKiaQ&cb_client=search.gws-prod.gps&w=800&h=500&yaw=94.0714&pitch=0&thumbfov=100",
      "working_hours": {
        "Friday": "Closed",
        "Monday": "9AM-4PM",
        "Saturday": "Closed",
        "Sunday": "Closed",
        "Thursday": "9AM-4PM",
        "Tuesday": "9AM-4PM",
        "Wednesday": "9AM-4PM"
      },
      "reviews_per_score": {
        "1": 0,
        "2": 0,
        "3": 0,
        "4": 0,
        "5": 11
      },
      "business_status": "OPERATIONAL",
      "is_verified": true,
      "is_claimed": true
    },
    {
      "slug": "kevin-m-harris-cpa-cfp",
      "name": "Kevin M. Harris, CPA, CFP",
      "category": "Accounting firm",
      "phone": "+1 615-866-0589",
      "site": "http://www.kevinmharris.com/",
      "address": "354 Cool Springs Blvd #103, Franklin, TN 37067",
      "latitude": 35.9434026,
      "longitude": -86.8282929,
      "rating": 0,
      "reviews": 0,
      "logo": "https://lh5.googleusercontent.com/-60cktAtOXek/AAAAAAAAAAI/AAAAAAAAAAA/aI8_HNKtaYo/s44-p-k-no-ns-nd/photo.jpg",
      "photo": "https://streetviewpixels-pa.googleapis.com/v1/thumbnail?panoid=Of6gkIJXEphL8EJD9YtQQQ&cb_client=search.gws-prod.gps&w=800&h=500&yaw=205.41557&pitch=0&thumbfov=100",
      "working_hours": {
        "Friday": "8:30AM-5PM",
        "Monday": "8:30AM-5PM",
        "Saturday": "Closed",
        "Sunday": "Closed",
        "Thursday": "8:30AM-5PM",
        "Tuesday": "8:30AM-5PM",
        "Wednesday": "8:30AM-5PM"
      },
      "reviews_per_score": {
        "1": 0,
        "2": 0,
        "3": 0,
        "4": 0,
        "5": 0
      },
      "business_status": "OPERATIONAL",
      "is_verified": true,
      "is_claimed": true
    },
    {
      "slug": "tom-wall-cpa-pllc",
      "name": "Tom Wall CPA PLLC",
      "category": "Bookkeeping service",
      "phone": "+1 615-771-9688",
      "site": "",
      "address": "256 Seaboard Ln ste e-103, Franklin, TN 37067",
      "latitude": 35.9525492,
      "longitude": -86.82689979999999,
      "rating": 0,
      "reviews": 0,
      "logo": "https://lh6.googleusercontent.com/-Lk-iqh-GlS4/AAAAAAAAAAI/AAAAAAAAAAA/iu9a9V0qqIY/s44-p-k-no-ns-nd/photo.jpg",
      "photo": "https://streetviewpixels-pa.googleapis.com/v1/thumbnail?panoid=kTru7HtZG-guNJSnKEYXLg&cb_client=search.gws-prod.gps&w=800&h=500&yaw=268.5169&pitch=0&thumbfov=100",
      "working_hours": {
        "Friday": "8AM-5PM",
        "Monday": "8AM-5PM",
        "Saturday": "Closed",
        "Sunday": "Closed",
        "Thursday": "8AM-5PM",
        "Tuesday": "8AM-5PM",
        "Wednesday": "8AM-5PM"
      },
      "reviews_per_score": {
        "1": 0,
        "2": 0,
        "3": 0,
        "4": 0,
        "5": 0
      },
      "business_status": "OPERATIONAL",
      "is_verified": true,
      "is_claimed": true
    }
  ]
}